[
    {
        "w": "冷凍室",
        "p": "lěngdòngshì",
        "m": "Ngăn đá",
        "m_en": "Freezer",
        "m_ru": "морозильная камера",
        "m_ko": "냉동실",
        "m_ja": "冷凍室: 冷凍庫",
        "m_th": "ช่องแช่แข็ง",
        "m_id": "Ruang pembeku",
        "m_ms": "Petak beku",
        "unit": 8
    },
    {
        "w": "粉末混合机",
        "p": "fěnmò hùnhé jī",
        "m": "Máy trộn bột",
        "m_en": "Powder Mixer",
        "m_ru": "порошковая смесительная машина",
        "m_ko": "분말 혼합기",
        "m_ja": "粉体混合機",
        "m_th": "เครื่องผสมผง",
        "m_id": "Mesin pencampur bubuk",
        "m_ms": "Mesin pengadun serbuk",
        "unit": 8
    },
    {
        "w": "柠檬榨汁机",
        "p": "níngméng zhà zhī jī",
        "m": "Máy ép chanh",
        "m_en": "Lemon Squeezer",
        "m_ru": "цитрусовая соковыжималка",
        "m_ko": "레몬 주스 기계",
        "m_ja": "レモン絞り機",
        "m_th": "เครื่องคั้นน้ำมะนาว",
        "m_id": "Pemeras Jeruk Nipis",
        "m_ms": "Pemeras Jus Lemon",
        "unit": 8
    },
    {
        "w": "滤斗",
        "p": "lǜ dǒu",
        "m": "Phễu lọc",
        "m_en": "Filter Funnel",
        "m_ru": "воронка (для переливания)",
        "m_ko": "여과용 깔때기。",
        "m_ja": "フィルター",
        "m_th": "กรวยกรอง",
        "m_id": "Corong penyaring",
        "m_ms": "Corong penapis",
        "unit": 8
    },
    {
        "w": "签",
        "p": "qiān",
        "m": "Tăm",
        "m_en": "Skewer",
        "m_ru": "бирка; отметка",
        "m_ko": "서명하다。 사인(sign)하다。; (요점·의견 따위를 나타내기 위해) 간단하게 몇 자 적다。",
        "m_ja": "（〜儿）〔‘个・根［儿］’＋〕（占い・賭博・ゲームなどに用いる文字や符号を刻んだ細長い竹や木の棒）札，くじ．≡佥2．; 〔‘个・张’＋〕（標識にする）紙片，短冊．≡佥2．; 〔‘根［儿］’＋〕（竹や木を削って作った）とがった細い棒．≡佥2．",
        "m_th": "แท่ง; แผ่น",
        "m_id": "Tongkat; kartu",
        "m_ms": "Batang; kad",
        "unit": 8
    },
    {
        "w": "土豆捣碎机",
        "p": "tǔdòu dǎo suì jī",
        "m": "Máy nghiền khoai tây",
        "m_en": "Potato Masher",
        "m_ru": "картофельный пресс",
        "m_ko": "감자 으깨는 기계",
        "m_ja": "ポテトマッシャー",
        "m_th": "เครื่องบดมันฝรั่ง",
        "m_id": "Mesin penghalus kentang",
        "m_ms": "Mesin penghancur kentang",
        "unit": 8
    },
    {
        "w": "打蛋器",
        "p": "dǎ dàn qì",
        "m": "Máy đánh trứng",
        "m_en": "Egg Beater",
        "m_ru": "взбивалка для яиц, венчик, миксер",
        "m_ko": "거품기。",
        "m_ja": "泡立て器",
        "m_th": "เครื่องตีไข่",
        "m_id": "Mixer telur",
        "m_ms": "Pemukul telur",
        "unit": 8
    },
    {
        "w": "榨果汁机",
        "p": "zhà guǒzhī jī",
        "m": "Máy ép hoa quả",
        "m_en": "Juicer",
        "m_ru": "соковыжималка",
        "m_ko": "주스 기계",
        "m_ja": "ジュースメーカー",
        "m_th": "เครื่องคั้นน้ำผลไม้",
        "m_id": "Mesin pemeras buah",
        "m_ms": "Mesin pemerah jus buah",
        "unit": 8
    },
    {
        "w": "融化",
        "p": "rónghuà",
        "m": "Tan, hòa tan",
        "m_en": "Melt",
        "m_ru": "растворяться; таять",
        "m_ko": "(얼음·눈 따위가) 녹다。 융해되다。",
        "m_ja": "（氷・雪・霜が水に）解ける，融解する．≡溶化2．≒融解．",
        "m_th": "ละลาย; ละลาย (น้ำแข็ง, หิมะ...)",
        "m_id": "Mencair; meleleh",
        "m_ms": "Cair; mencair",
        "unit": 8
    },
    {
        "w": "洗",
        "p": "xǐ",
        "m": "Rửa",
        "m_en": "Wash",
        "m_ru": "мыть, отмывать; стирать",
        "m_ko": "씻다。; 누명이나 수치를 씻다。; 깨끗이 제거하다。 쓸어버리다。 숙청하다。 제명하다。",
        "m_ja": "（水・ベンジンなどで物体の汚れを）洗う，すすぐ．濯; 水浴びする，入浴する．; 皆殺しにする，奪い尽くす．",
        "m_th": "ล้าง; ซัก",
        "m_id": "Mencuci; mencuci pakaian",
        "m_ms": "mencuci; membasuh",
        "unit": 8
    },
    {
        "w": "吸管",
        "p": "xīguǎn",
        "m": "Ống hút",
        "m_en": "Straw",
        "m_ru": "трубка (курительная); соломинка",
        "m_ko": "〈기계〉 흡입관。; 빨대。 스트로(straw)。",
        "m_ja": "サクションパイプ",
        "m_th": "หลอดดูด; หลอด",
        "m_id": "Sedotan; Sedotan",
        "m_ms": "Penyedut minuman; Tiub",
        "unit": 8
    },
    {
        "w": "添加",
        "p": "tiānjiā",
        "m": "Cho thêm",
        "m_en": "Add",
        "m_ru": "добавлять; надбавлять",
        "m_ko": "첨가하다。 늘리다。 보태다。",
        "m_ja": "添い",
        "m_th": "เพิ่ม; เพิ่มเข้าไป",
        "m_id": "menambahkan; menambah",
        "m_ms": "tambah; menambah",
        "unit": 8
    },
    {
        "w": "倒",
        "p": "dào",
        "m": "Rót, đổ",
        "m_en": "Pour",
        "m_ru": "dǎo падать, валиться; переворачиваться, опрокидываться",
        "m_ko": "(사람 또는 똑바로 서 있는 것이) (옆으로) 넘어지다。 자빠지다。; (사업이) 실패하다。 도산하다。 망하다。; (반정부 활동 등으로) 정부나 수뇌 인물이 쓰러지다。",
        "m_ja": "（上下・前後・左右・表裏が）逆になる，逆さまになる．注ぎたい．濺ぎ．濺がれる．注いでいない; （上下・前後・左右・表裏を）逆にする，逆さまにする．; （容器をひっくり返したり傾けたりして中身を）空ける，注ぐ，捨てる．",
        "m_th": "เท; ริน",
        "m_id": "Tuang; tumpahkan",
        "m_ms": "Tuang; curah",
        "unit": 8
    },
    {
        "w": "筛子",
        "p": "shāizi",
        "m": "Cái sàng, cái rây",
        "m_en": "Sieve",
        "m_ru": "решето; сито",
        "m_ko": "체。",
        "m_ja": "〔‘个’＋〕ふるい．",
        "m_th": "ตะแกรง; ร่อน",
        "m_id": "Saringan",
        "m_ms": "penapis; saringan",
        "unit": 8
    },
    {
        "w": "混合",
        "p": "hùnhé",
        "m": "Hỗn hợp, trộn, nhào",
        "m_en": "Mix",
        "m_ru": "смесь; смешивать",
        "m_ko": "혼합하다。 함께 섞다。",
        "m_ja": "（異種類のものを）混ぜ合わす，混じり合う．ミキシング．メドレー．ブレンド．ミックス",
        "m_th": "ผสม; รวม",
        "m_id": "Campuran; mencampur",
        "m_ms": "Campuran; campur",
        "unit": 8
    },
    {
        "w": "撕开",
        "p": "sī kāi",
        "m": "Xé ra",
        "m_en": "Tear",
        "m_ru": "разорвать (бумагу; платок)",
        "m_ko": "찢어 버리다。 두 갈래로 찢다。",
        "m_ja": "裂きますれば",
        "m_th": "ฉีก; ฉีกออก",
        "m_id": "Merobek; merobek keluar",
        "m_ms": "Mengoyakkan; merobek",
        "unit": 8
    },
    {
        "w": "加热",
        "p": "jiārè",
        "m": "Làm nóng",
        "m_en": "Heat",
        "m_ru": "нагревать, подогревать; нагревание, нагрев",
        "m_ko": "가열하다。",
        "m_ja": "加熱する，熱くする．ヒーチング．ウォーミング",
        "m_th": "เพิ่มความร้อน; ทำให้ร้อน",
        "m_id": "Memanaskan; menghangatkan",
        "m_ms": "meningkatkan suhu; memanaskan",
        "unit": 8
    },
    {
        "w": "拌搅机",
        "p": "bàn jiǎo jī",
        "m": "Máy xay sinh tố",
        "m_en": "Blender",
        "m_ru": "Смешиватель",
        "m_ko": "혼합기",
        "m_ja": "ブレンダー",
        "m_th": "เครื่องปั่น",
        "m_id": "Blender",
        "m_ms": "Pengisar",
        "unit": 8
    },
    {
        "w": "揉",
        "p": "róu",
        "m": "Vò, vê, nặn",
        "m_en": "Knead",
        "m_ru": "тереть; массировать",
        "m_ko": "(손으로) 비비다。 문지르다。 주무르다。; (손으로 둥글게) 빚다。 이기다。 반죽하다。; 【문어】 (물건을) 구부리다。 휘다。 →[揉轮]",
        "m_ja": "（てのひらで体を）もむ，こする，さする．; （服などを洗うために）もむ，もみ洗いする．; （練った小麦粉や泥・紙などを両手のてのひらで球状にするために）こねる，こねて丸める，もんで丸める．",
        "m_th": "ถู; ขยี้",
        "m_id": "Menggosok; meremas",
        "m_ms": "Menggosok; menguli",
        "unit": 8
    },
    {
        "w": "拍碎",
        "p": "pāi suì",
        "m": "Đập dập",
        "m_en": "Smash",
        "m_ru": "разбить на куски",
        "m_ko": "부수다",
        "m_ja": "砕く",
        "m_th": "ทุบให้แตก",
        "m_id": "Dipukul hingga hancur",
        "m_ms": "Pecahkan",
        "unit": 8
    },
    {
        "w": "压碎",
        "p": "yā suì",
        "m": "Nghiền nát, nghiền vụn",
        "m_en": "Crush",
        "m_ru": "раздавливать, расплющивать; геол. деформация среза",
        "m_ko": "뭉게다。 으깨다。",
        "m_ja": "ひしいでいる",
        "m_th": "บดขยี้",
        "m_id": "Menghancurkan; menghancurkan menjadi serpihan",
        "m_ms": "Menghancurkan; menghancurkan menjadi serpihan",
        "unit": 8
    },
    {
        "w": "拌",
        "p": "bàn",
        "m": "Trộn",
        "m_en": "Mix",
        "m_ru": "bàn мешать, смешивать; размешивать",
        "m_ko": "뒤섞다。 이기다。 버무리다。; 말다툼하다。",
        "m_ja": "（土砂・食物・えさなどを）かき混ぜる，混ぜ合わせる，攪拌する．⇒搅拌 jiǎobàn ，凉拌 liángbàn ，杂拌儿 zábànr ．汚していないらしいです．汚す．汚さなそうならば",
        "m_th": "ผสม; คลุกเคล้า",
        "m_id": "mencampur; mengaduk",
        "m_ms": "Campur; gaul",
        "unit": 8
    },
    {
        "w": "搅打",
        "p": "jiǎo dǎ",
        "m": "Trộng, quấy, đánh",
        "m_en": "Beat (egg, cream)",
        "m_ru": "взбивать",
        "m_ko": "휘젓다",
        "m_ja": "かき混ぜる",
        "m_th": "ตี, ผสม, คน",
        "m_id": "Mengaduk",
        "m_ms": "Kacau, gaul, pukul",
        "unit": 8
    },
    {
        "w": "珩磨钢",
        "p": "hángmó gāng",
        "m": "Thanh mài dao",
        "m_en": "Sharpening steel",
        "m_ru": "шлифовальная сталь",
        "m_ko": "연마강",
        "m_ja": "ハンマ鋼",
        "m_th": "แท่งลับมีด",
        "m_id": "Bilah pengasah pisau",
        "m_ms": "Batang pengasah pisau",
        "unit": 7
    },
    {
        "w": "水龍頭",
        "p": "shuǐlóngtóu",
        "m": "Vòi nước",
        "m_en": "Faucet",
        "m_ru": "водяной кран",
        "m_ko": "수도꼭지",
        "m_ja": "水道の蛇口",
        "m_th": "ก๊อกน้ำ",
        "m_id": "Keran air",
        "m_ms": "Paip air",
        "unit": 7
    },
    {
        "w": "超级热水器",
        "p": "chāojí rèshuǐ qì",
        "m": "Bình siêu tốc",
        "m_en": "Instant water heater",
        "m_ru": "супер водонагреватель",
        "m_ko": "슈퍼 온수기",
        "m_ja": "スーパーケトル",
        "m_th": "เครื่องทำน้ำร้อนเร็วพิเศษ",
        "m_id": "Pemanas air super cepat",
        "m_ms": "Pemanas air super cepat",
        "unit": 7
    },
    {
        "w": "冰箱除臭剂",
        "p": "bīngxiāng chú chòu jì",
        "m": "Thuốc khử mùi hôi trong tủ lạnh",
        "m_en": "Refrigerator Deodorizer",
        "m_ru": "освежитель для холодильника",
        "m_ko": "냉장고 탈취제",
        "m_ja": "冷蔵庫用消臭剤",
        "m_th": "ยาดับกลิ่นในตู้เย็น (ห้องครัว)",
        "m_id": "Obat penghilang bau di lemari es (Dapur)",
        "m_ms": "Ejen penghilang bau dalam peti sejuk (Dapur)",
        "unit": 7
    },
    {
        "w": "排风扇",
        "p": "páifēngshàn",
        "m": "Quạt hút gió",
        "m_en": "Exhaust Fan",
        "m_ru": "вытяжной вентилятор",
        "m_ko": "환기용 선풍기。 송풍기。 통풍기。  [通tōng风扇]",
        "m_ja": "換気扇．≒排气扇．",
        "m_th": "พัดลมดูดอากาศ; พัดลมระบายอากาศ",
        "m_id": "kipas ventilasi",
        "m_ms": "Kipas ekzos",
        "unit": 7
    },
    {
        "w": "生炉手套",
        "p": "shēng lú shǒutào",
        "m": "Găng tay làm bếp",
        "m_en": "Oven Mitts",
        "m_ru": "перчатки для работы с печью",
        "m_ko": "생로 손장갑",
        "m_ja": "調理用手袋",
        "m_th": "ถุงมือทำครัว, ถุงมือกันความร้อน",
        "m_id": "Sarung tangan dapur, sarung tangan tahan panas",
        "m_ms": "Sarung tangan dapur, sarung tangan tahan panas",
        "unit": 7
    },
    {
        "w": "温度计",
        "p": "wēn dùjì",
        "m": "Nhiệt kế",
        "m_en": "Thermometer",
        "m_ru": "градусник, термометр, термопара",
        "m_ko": "온도계。",
        "m_ja": "温度计．ヒートインジケータ．温度計．おんど計",
        "m_th": "เครื่องวัดอุณหภูมิ; เทอร์โมมิเตอร์",
        "m_id": "Termometer; termometer suhu",
        "m_ms": "Termometer; alat pengukur suhu",
        "unit": 7
    },
    {
        "w": "火柴",
        "p": "huǒchái",
        "m": "Diêm",
        "m_en": "Match",
        "m_ru": "спички",
        "m_ko": "성냥。",
        "m_ja": "〔‘根・盒［儿］・包［儿］’＋〕マッチ．≒洋火，安全火柴．",
        "m_th": "ไม้ขีดไฟ; ไม้ขีด",
        "m_id": "Korek api",
        "m_ms": "Mancis",
        "unit": 7
    },
    {
        "w": "咖啡机",
        "p": "kāfēi jī",
        "m": "Máy pha cà phê",
        "m_en": "Coffee Machine",
        "m_ru": "кофемашина; кофеварка",
        "m_ko": "커피메이커",
        "m_ja": "コーヒーメーカー",
        "m_th": "เครื่องชงกาแฟ",
        "m_id": "Mesin pembuat kopi",
        "m_ms": "Mesin pembuat kopi",
        "unit": 7
    },
    {
        "w": "煤泥",
        "p": "méi ní",
        "m": "Bùn than",
        "m_en": "Coal slurry",
        "m_ru": "угольный шлам",
        "m_ko": "석탄 슬러지",
        "m_ja": "炭でい",
        "m_th": "โคลนถ่านหิน",
        "m_id": "Lumpur batubara",
        "m_ms": "Lumpur arang batu",
        "unit": 7
    },
    {
        "w": "蜂窝煤",
        "p": "fēngwōméi",
        "m": "Than tổ ong",
        "m_en": "Honeycomb coal",
        "m_ru": "сотовые угольные брикеты цилиндрической формы",
        "m_ko": "[명사] 구멍탄。 구공탄。  →[炭tàn基]; 십구공탄",
        "m_ja": "蜂窝煤の意味は、蜂の巣のような形状をした石炭の一種で、主に燃料として使用されるものです。",
        "m_th": "ถ่านอัดแท่ง",
        "m_id": "Briket arang",
        "m_ms": "Arang sarang lebah",
        "unit": 7
    },
    {
        "w": "空气机",
        "p": "kōngqì jī",
        "m": "Máy lọc không khí",
        "m_en": "Air purifier",
        "m_ru": "воздушный компрессор",
        "m_ko": "공기 기계",
        "m_ja": "空気清浄機",
        "m_th": "เครื่องฟอกอากาศ",
        "m_id": "Pemurni udara",
        "m_ms": "Penapis udara",
        "unit": 7
    },
    {
        "w": "烧",
        "p": "shāo",
        "m": "Xào",
        "m_en": "Stir-fry",
        "m_ru": "гореть; загораться",
        "m_ko": "태우다。 불사르다。; 가열하다。 끓이다。 (밥을) 짓다。 (벽돌 따위를) 굽다。; (조리법의 하나로) 기름으로 튀기거나 볶은 다음에, 국물을 붓고 다시 볶거나 고다。 먼저 익힌 다음에 기름으로 볶다。",
        "m_ja": "（物が）焼ける，燃える．たきたがらなかろう．たきたがり．たいているそうです．たくのでしたらば; （物を）焼く，燃やす．; （木・粘土・米・水などに熱を加えて炭・れんが・ご飯・湯などを）焼く，炊く，沸かす．",
        "m_th": "เผา; ไหม้",
        "m_id": "Membakar; membakar",
        "m_ms": "Bakar; membakar",
        "unit": 7
    },
    {
        "w": "红光炉",
        "p": "hóngguāng lú",
        "m": "Bếp hồng ngoại",
        "m_en": "Infrared cooker",
        "m_ru": "красный светильник",
        "m_ko": "홍광로",
        "m_ja": "赤外線コンロ",
        "m_th": "เตาอินฟราเรด",
        "m_id": "Kompor inframerah",
        "m_ms": "Dapur inframerah",
        "unit": 7
    },
    {
        "w": "烤面包机",
        "p": "kǎo miànbāo jī",
        "m": "Lò nướng bánh mỳ",
        "m_en": "Toaster",
        "m_ru": "тостер",
        "m_ko": "토스터。",
        "m_ja": "トースター",
        "m_th": "เครื่องปิ้งขนมปัง",
        "m_id": "Pemanggang roti",
        "m_ms": "Pemanggang roti",
        "unit": 7
    },
    {
        "w": "灭火器",
        "p": "mièhuǒqì",
        "m": "Bình chữa cháy",
        "m_en": "Fire Extinguisher",
        "m_ru": "огнетушитель",
        "m_ko": "소화기",
        "m_ja": "消火器",
        "m_th": "ถังดับเพลิง",
        "m_id": "Alat pemadam api",
        "m_ms": "alat pemadam api",
        "unit": 7
    },
    {
        "w": "打火机",
        "p": "dǎhuǒjī",
        "m": "Bật lửa",
        "m_en": "Lighter",
        "m_ru": "зажигалка; стреляющий механизм",
        "m_ko": "라이터。",
        "m_ja": "ライター．",
        "m_th": "ไฟแช็ก",
        "m_id": "Pemantik api",
        "m_ms": "Pemetik api; pemetik api.",
        "unit": 7
    },
    {
        "w": "煤气热水器",
        "p": "méiqì rèshuǐqì",
        "m": "Bình nóng lạnh dùng ga",
        "m_en": "Gas Water Heater",
        "m_ru": "газовый водонагреватель",
        "m_ko": "가스 온수기",
        "m_ja": "ガス給湯器",
        "m_th": "เครื่องทำน้ำอุ่นแก๊ส",
        "m_id": "Pemanas air gas",
        "m_ms": "Pemanas air gas",
        "unit": 7
    },
    {
        "w": "烧烤机",
        "p": "shāokǎo jī",
        "m": "Máy nướng thịt",
        "m_en": "Barbecue grill",
        "m_ru": "гриль",
        "m_ko": "바베큐 기계",
        "m_ja": "焼肉機",
        "m_th": "เครื่องย่างบาร์บีคิว",
        "m_id": "Pemanggang daging",
        "m_ms": "Pemanggang daging",
        "unit": 7
    },
    {
        "w": "油烟机",
        "p": "yóu yān jī",
        "m": "Máy hút mùi",
        "m_en": "Range Hood",
        "m_ru": "вытяжка",
        "m_ko": "후드",
        "m_ja": "レンジフード",
        "m_th": "เครื่องดูดควัน; พัดลมระบายอากาศ",
        "m_id": "Mesin penghisap asap; kipas ventilasi",
        "m_ms": "Penghisap asap; kipas pengudaraan",
        "unit": 7
    },
    {
        "w": "微波炉",
        "p": "wéibōlú",
        "m": "Lò vi sóng",
        "m_en": "Microwave Oven",
        "m_ru": "микроволновая печь; разг. микроволновка",
        "m_ko": "마이크로웨이브 스토브。 극초단파 난로(煖爐)。",
        "m_ja": "电子レンジ",
        "m_th": "เตาไมโครเวฟ",
        "m_id": "Microwave",
        "m_ms": "Ketuhar gelombang mikro",
        "unit": 7
    },
    {
        "w": "烤箱",
        "p": "kǎoxiāng",
        "m": "Lò nướng",
        "m_en": "Oven",
        "m_ru": "шкаф для жарения; духовка",
        "m_ko": "오븐(oven)。 레인지。",
        "m_ja": "〔‘个・台’＋〕オーブン．",
        "m_th": "เตาอบ",
        "m_id": "Oven",
        "m_ms": "Ketuhar",
        "unit": 7
    },
    {
        "w": "电磁炉",
        "p": "diàncílú",
        "m": "Bếp từ",
        "m_en": "Induction Cooker",
        "m_ru": "индукционная плита",
        "m_ko": "전자로。",
        "m_ja": "電磁調理器",
        "m_th": "เตาแม่เหล็กไฟฟ้า; เตาไฟฟ้าแม่เหล็ก",
        "m_id": "Kompor induksi listrik",
        "m_ms": "Dapur induksi",
        "unit": 7
    },
    {
        "w": "煤气炉",
        "p": "méiqì lú",
        "m": "Bếp ga",
        "m_en": "Gas Stove",
        "m_ru": "газовая печь",
        "m_ko": "가스레인지。  [瓦斯炉]; 가스오븐",
        "m_ja": "ガスコンロ",
        "m_th": "เตาแก๊ส",
        "m_id": "Kompor gas",
        "m_ms": "Dapur gas",
        "unit": 7
    },
    {
        "w": "弹簧秤",
        "p": "tánhuángchèng",
        "m": "Cân lò xo",
        "m_en": "Spring scale",
        "m_ru": "пружинные весы, ручные пружинные весы, безмен",
        "m_ko": "용수철저울。",
        "m_ja": "スプリングバランス",
        "m_th": "เครื่องชั่งสปริง",
        "m_id": "Timbangan pegas",
        "m_ms": "Timbangan spring",
        "unit": 6
    },
    {
        "w": "电子秤",
        "p": "diànzǐ chèng",
        "m": "Cân điện tử",
        "m_en": "Electronic scale",
        "m_ru": "электронные весы",
        "m_ko": "전자저울。",
        "m_ja": "エレクトロニックスケール",
        "m_th": "เครื่องชั่งน้ำหนักอิเล็กทรอนิกส์",
        "m_id": "Timbangan elektronik",
        "m_ms": "Timbangan elektronik",
        "unit": 6
    },
    {
        "w": "圧蒜器",
        "p": "yā suàn qì",
        "m": "Máy ép tỏi",
        "m_en": "Garlic Press",
        "m_ru": "давилка для чеснока",
        "m_ko": "압마늘기계",
        "m_ja": "にんにくプレス",
        "m_th": "เครื่องบดกระเทียม",
        "m_id": "Alat pemeras bawang putih",
        "m_ms": "Alat penekan bawang putih",
        "unit": 6
    },
    {
        "w": "刨冰机",
        "p": "bàobīng jī",
        "m": "Máy bào đá",
        "m_en": "Shaved Ice Machine",
        "m_ru": "льдодробилка",
        "m_ko": "빙수기",
        "m_ja": "かき氷機",
        "m_th": "เครื่องไสน้ำแข็ง",
        "m_id": "Mesin serut es",
        "m_ms": "Mesin pencukur ais",
        "unit": 6
    },
    {
        "w": "烤肉叉",
        "p": "kǎoròu chā",
        "m": "Xiên nướng thịt",
        "m_en": "Barbecue Fork",
        "m_ru": "вилка для жареного мяса, шампур, вертел",
        "m_ko": "고기 굽는 포크",
        "m_ja": "焼肉フォーク",
        "m_th": "ไม้เสียบเนื้อย่าง",
        "m_id": "Tusuk sate",
        "m_ms": "Daging panggang cucuk",
        "unit": 6
    },
    {
        "w": "扫帚",
        "p": "sàozhou",
        "m": "Cái chổi",
        "m_en": "Broom",
        "m_ru": "метла; веник",
        "m_ko": "비。 빗자루。 마당비。 [‘笤tiáo帚’보다 큼]",
        "m_ja": "〔‘把’＋〕（道路・庭を掃くための大きな）竹ぼうき．⇒笤帚 tiáo・zhou ．",
        "m_th": "ไม้กวาด",
        "m_id": "Sapu",
        "m_ms": "Penyapu; sapu",
        "unit": 6
    },
    {
        "w": "剥皮器",
        "p": "bāopí qì",
        "m": "Cái nạo",
        "m_en": "Peeler",
        "m_ru": "зазывалка, стриптизерша",
        "m_ko": "껍질 벗기는 기계",
        "m_ja": "皮むき器",
        "m_th": "เครื่องปอกเปลือก",
        "m_id": "Alat pengupas",
        "m_ms": "Alat pengupas",
        "unit": 6
    },
    {
        "w": "火钳",
        "p": "huǒqián",
        "m": "Kẹp gắp than",
        "m_en": "Tongs",
        "m_ru": "щипцы (каминные); клещи (кузнечные)",
        "m_ko": "불집게。 부집게。; 연탄집게",
        "m_ja": "≒火剪 huǒjiǎn ①．火突き棒．ポーカー",
        "m_th": "ที่คีบถ่าน; คีมคีบถ่าน",
        "m_id": "Penjepit bara; penjepit arang",
        "m_ms": "Penjepit arang",
        "unit": 6
    },
    {
        "w": "套刀",
        "p": "tào dāo",
        "m": "Dao theo bộ",
        "m_en": "Knife Set",
        "m_ru": "набор ножей",
        "m_ko": "세트 칼",
        "m_ja": "セットナイフ",
        "m_th": "ชุดมีด",
        "m_id": "Satu set pisau",
        "m_ms": "Set pisau",
        "unit": 6
    },
    {
        "w": "磨刀石",
        "p": "mó dāo shí",
        "m": "Đá mài dao",
        "m_en": "Knife Sharpener",
        "m_ru": "точильный камень, брусок, оселок",
        "m_ko": "숫돌。  [【문어】 硎(1)]",
        "m_ja": "砥石",
        "m_th": "หินลับมีด",
        "m_id": "Batu asah pisau",
        "m_ms": "Batu asah pisau",
        "unit": 6
    },
    {
        "w": "切片",
        "p": "qiēpiàn",
        "m": "Thái thành miếng",
        "m_en": "Slice",
        "m_ru": "срез; делать срезы",
        "m_ko": "물체를 얇게 자르다。",
        "m_ja": "〔‘个・块［儿］’＋〕（顕微鏡用の）薄片．",
        "m_th": "หั่นบาง ๆ; ชิ้นส่วน",
        "m_id": "Mengiris tipis; memotong tipis",
        "m_ms": "Menghiris nipis; menghiris",
        "unit": 6
    },
    {
        "w": "绞肉器",
        "p": "jiǎo ròu qì",
        "m": "Máy xay thịt",
        "m_en": "Meat Grinder",
        "m_ru": "мясорубка",
        "m_ko": "다진 고기 기계",
        "m_ja": "ミンチ機",
        "m_th": "เครื่องบดเนื้อ",
        "m_id": "Penggiling daging",
        "m_ms": "Pengisar daging",
        "unit": 6
    },
    {
        "w": "面包刀",
        "p": "miànbāo dāo",
        "m": "Dao cắt bánh mì",
        "m_en": "Bread knife",
        "m_ru": "нож для хлеба, хлебный нож",
        "m_ko": "빵칼",
        "m_ja": "パンナイフ",
        "m_th": "มีดตัดขนมปัง",
        "m_id": "Pisau roti",
        "m_ms": "Pisau roti",
        "unit": 6
    },
    {
        "w": "削皮",
        "p": "xiāo pí",
        "m": "Gọt vỏ",
        "m_en": "Peel",
        "m_ru": "очищать от скорлупы (кожуры); чистить",
        "m_ko": "껍질을 벗기다[깎다]。",
        "m_ja": "皮をむく",
        "m_th": "ปอกเปลือก; ลอกเปลือก",
        "m_id": "Mengupas kulit; mengupas",
        "m_ms": "Mengupas kulit",
        "unit": 6
    },
    {
        "w": "斩骨刀",
        "p": "zhǎn gǔ dāo",
        "m": "Dao chặt xương",
        "m_en": "Cleaver",
        "m_ru": "нож для резки костей",
        "m_ko": "절골도",
        "m_ja": "骨を切るための刀",
        "m_th": "มีดสับกระดูก",
        "m_id": "Pisau pemotong daging",
        "m_ms": "Pisau pemotong (pisau); pisau besar (pisau)",
        "unit": 6
    },
    {
        "w": "砧板",
        "p": "zhēnbǎn",
        "m": "Thớt gỗ",
        "m_en": "Cutting Board",
        "m_ru": "кухонная доска, разделочная доска; плаха",
        "m_ko": "도마。",
        "m_ja": "〔‘块’＋〕まないた．≒案板，菜墩子，切 qiē 菜板．",
        "m_th": "เขียงไม้",
        "m_id": "Papan pemotong kayu",
        "m_ms": "Papan pemotong kayu",
        "unit": 6
    },
    {
        "w": "切",
        "p": "qiè",
        "m": "Cắt, bổ, thái",
        "m_en": "Cut",
        "m_ru": "qiē резать, нарезать; разрезать, рассекать",
        "m_ko": "딱 들어맞다。 맞물리다。 밀접하다。 부합되다。; 【문어】 진맥하다。 맥을 짚다。; 【북경어】【구어】 노름하다。 도박하다。 [북경 청소년 사이에 유행하는 말] →[切份儿]",
        "m_ja": "ぴったり合う，適合する．⇒贴切 tiēqiè ．",
        "m_th": "ธรณีประตู; ขั้นบันได",
        "m_id": "Ambang; anak tangga",
        "m_ms": "Ambang; tangga pintu",
        "unit": 6
    },
    {
        "w": "多功能刀",
        "p": "duō gōngnéng dāo",
        "m": "Dao đa chức năng",
        "m_en": "Multi-purpose knife",
        "m_ru": "многофункциональный нож",
        "m_ko": "다기능 칼",
        "m_ja": "マルチツールナイフ",
        "m_th": "มีดอเนกประสงค์",
        "m_id": "Pisau serbaguna",
        "m_ms": "Pisau serbaguna",
        "unit": 6
    },
    {
        "w": "叉子",
        "p": "chāzi",
        "m": "Cái nĩa",
        "m_en": "Fork",
        "m_ru": "вилка; ухват",
        "m_ko": "양식용 포크。; 농업용 갈고랑이。 [수확용 또는 퇴비를 다룰 때 씀]; 부인의 머리에 꽂는 핀의 일종。",
        "m_ja": "〔‘只 zhī ’＋〕フォーク．クレビス",
        "m_th": "ส้อม; จาน",
        "m_id": "Garpu; Garpu tiga",
        "m_ms": "Garpu; Garpu tiga",
        "unit": 6
    },
    {
        "w": "水果刀",
        "p": "shuǐguǒ dāo",
        "m": "Dao gọt hoa quả",
        "m_en": "Fruit Knife",
        "m_ru": "ножичек для фруктов; буфетный нож",
        "m_ko": "과도。 과일(깎는)칼。",
        "m_ja": "フルーツナイフ",
        "m_th": "มีดปอกผลไม้",
        "m_id": "Pisau buah",
        "m_ms": "Pisau buah",
        "unit": 6
    },
    {
        "w": "剪刀",
        "p": "jiǎndāo",
        "m": "Kéo",
        "m_en": "Scissors",
        "m_ru": "ножницы",
        "m_ko": "가위。; 전단기(剪斷機)。 시어(shear)。",
        "m_ja": "〔‘把’＋〕はさみ．≒剪子．鋏",
        "m_th": "กรรไกร",
        "m_id": "Gunting; alat pemotong",
        "m_ms": "Gunting; sepasang gunting",
        "unit": 6
    },
    {
        "w": "剔骨刀",
        "p": "tī gǔ dāo",
        "m": "Dao lọc xương",
        "m_en": "Boning knife",
        "m_ru": "нож для обрезки костей",
        "m_ko": "골절 칼",
        "m_ja": "骨を削る刀",
        "m_th": "มีดเลาะกระดูก",
        "m_id": "Pisau pemisah tulang",
        "m_ms": "Pisau pemisah tulang",
        "unit": 6
    },
    {
        "w": "切肉刀",
        "p": "qiē ròu dāo",
        "m": "Dao cắt thịt",
        "m_en": "Carving knife",
        "m_ru": "нож для разделки мяса",
        "m_ko": "고기를 써는 데 쓰는 큰 칼",
        "m_ja": "クリーバー",
        "m_th": "มีดหั่นเนื้อ",
        "m_id": "Pisau pemotong daging",
        "m_ms": "Pisau pemotong daging",
        "unit": 6
    },
    {
        "w": "刀叉",
        "p": "dāo chā",
        "m": "Dao nĩa",
        "m_en": "Knife and Fork",
        "m_ru": "нож и вилка; столовый прибор (европейского образца)",
        "m_ko": "나이프와 포크。",
        "m_ja": "ナイフとフォーク．",
        "m_th": "มีดและส้อม",
        "m_id": "Pisau dan garpu",
        "m_ms": "Pisau dan garpu",
        "unit": 6
    },
    {
        "w": "紙杯",
        "p": "zhǐbēi",
        "m": "Cốc giấy",
        "m_en": "Paper cup",
        "m_ru": "бумажный стакан",
        "m_ko": "종이컵",
        "m_ja": "紙コップ",
        "m_th": "แก้วกระดาษ",
        "m_id": "Gelas kertas",
        "m_ms": "Cawan kertas",
        "unit": 5
    },
    {
        "w": "垃圾箱",
        "p": "lājī xiāng",
        "m": "Thùng rác",
        "m_en": "Trash can",
        "m_ru": "мусорный ящик; урна для мусора",
        "m_ko": "(상자모양으로 된) 쓰레기통。",
        "m_ja": "ごみ箱．ゴミ箱．ゴミばこ",
        "m_th": "ถังขยะ",
        "m_id": "Tempat sampah",
        "m_ms": "Tong sampah",
        "unit": 5
    },
    {
        "w": "垃圾桶",
        "p": "lèsè tǒng",
        "m": "Thùng rác",
        "m_en": "Trash Can",
        "m_ru": "контейнер для мусора; ведро для отбросов",
        "m_ko": "쓰레기통。",
        "m_ja": "ごみ捨筒",
        "m_th": "ถังขยะ",
        "m_id": "Tempat sampah",
        "m_ms": "Tong sampah",
        "unit": 5
    },
    {
        "w": "滴流咖啡壶",
        "p": "dī liú kāfēi hú",
        "m": "Bình cà phê phin",
        "m_en": "Drip coffee pot",
        "m_ru": "кофейный автомат",
        "m_ko": "드립 커피 포트",
        "m_ja": "ドリップコーヒーポット",
        "m_th": "เครื่องชงกาแฟดริป",
        "m_id": "Teko kopi tetes (Dapur)",
        "m_ms": "Penapis kopi titisan (Dapur)",
        "unit": 5
    },
    {
        "w": "水槽",
        "p": "shuǐcáo",
        "m": "Chậu rửa bát",
        "m_en": "Sink",
        "m_ru": "раковина (обычно кухонная); водяной жёлоб",
        "m_ko": "물통。 물탱크。",
        "m_ja": "水槽．タンク．水ため．フリューム．深皿",
        "m_th": "ถังเก็บน้ำ",
        "m_id": "Tangki air",
        "m_ms": "Tangki air",
        "unit": 5
    },
    {
        "w": "调料瓶",
        "p": "tiáoliào píng",
        "m": "Hộp đựng gia vị",
        "m_en": "Seasoning bottle",
        "m_ru": "бутылка для приправ",
        "m_ko": "조미료 병",
        "m_ja": "調味料入れ",
        "m_th": "ขวดเครื่องปรุง",
        "m_id": "Botol bumbu",
        "m_ms": "Bekas rempah",
        "unit": 5
    },
    {
        "w": "冷藏室",
        "p": "lěngcángshì",
        "m": "Ngăn",
        "m_en": "Refrigerator",
        "m_ru": "холодильная камера",
        "m_ko": "냉장실",
        "m_ja": "冷蔵庫の中の部屋",
        "m_th": "ช่องแช่เย็น",
        "m_id": "Kompartemen lemari es",
        "m_ms": "Ruang peti sejuk",
        "unit": 5
    },
    {
        "w": "保鲜盒",
        "p": "bǎoxiān hé",
        "m": "Hộp bảo quản thực phẩm",
        "m_en": "Preservation box",
        "m_ru": "контейнер для хранения продуктов",
        "m_ko": "보관 용기",
        "m_ja": "食品保存容器",
        "m_th": "กล่องเก็บอาหาร",
        "m_id": "Kotak penyimpanan makanan",
        "m_ms": "Bekas penyimpanan makanan",
        "unit": 5
    },
    {
        "w": "热水袋",
        "p": "rè shuǐ dài",
        "m": "Túi chờm nóng",
        "m_en": "Hot water bottle",
        "m_ru": "(резиновая) грелка",
        "m_ko": "[명사] 더운물 주머니。 →[汤tāng壶]",
        "m_ja": "〔‘只 zhī ’＋〕（温湿布や保温用の湯を入れる）ゴム袋，湯たんぽ，ホットウォーターバッグ．",
        "m_th": "ถุงน้ำร้อน",
        "m_id": "Kantong air panas",
        "m_ms": "Beg air panas",
        "unit": 5
    },
    {
        "w": "冷冻柜",
        "p": "lěngdòng guì",
        "m": "Tủ đá",
        "m_en": "Freezer",
        "m_ru": "морозильный шкаф",
        "m_ko": "냉동고",
        "m_ja": "冷凍庫",
        "m_th": "ช่องแช่แข็ง",
        "m_id": "Laci pembeku",
        "m_ms": "Petak beku",
        "unit": 5
    },
    {
        "w": "保鲜袋",
        "p": "bǎoxiān dài",
        "m": "Túi bảo quản thực phẩm",
        "m_en": "Preservation bag",
        "m_ru": "пакет для хранения продуктов",
        "m_ko": "보관용 비닐봉지",
        "m_ja": "保存袋",
        "m_th": "ถุงเก็บรักษาความสด",
        "m_id": "Kantong penyimpanan",
        "m_ms": "Beg plastik penyimpanan",
        "unit": 5
    },
    {
        "w": "茶具",
        "p": "chájù",
        "m": "Dụng cụ uống trà",
        "m_en": "Tea set",
        "m_ru": "чайные принадлежности, чайная утварь; посуда и приборы для чаепития",
        "m_ko": "다구。 차제구(茶諸具)。 [차관(茶罐)·찻종·찻숟가락 등]; 차도구。차구",
        "m_ja": "〔‘套’・件’＋〕茶道具，茶器．ティーセット",
        "m_th": "ชุดน้ำชา",
        "m_id": "Perlengkapan teh; alat teh",
        "m_ms": "Set teh; peralatan teh",
        "unit": 5
    },
    {
        "w": "搪瓷杯",
        "p": "tángcí bēi",
        "m": "Cốc sứ, ly sứ",
        "m_en": "Enamel Cup",
        "m_ru": "глазурованный стакан; эмалированная чашка",
        "m_ko": "법랑컵",
        "m_ja": "エナメルカップ",
        "m_th": "ถ้วยเคลือบ, แก้วเคลือบ",
        "m_id": "Cangkir enamel, gelas enamel",
        "m_ms": "Cawan enamel, cawan seramik",
        "unit": 5
    },
    {
        "w": "储冰块器",
        "p": "chú bīng kuài qì",
        "m": "Khay đựng đá",
        "m_en": "Ice cube tray",
        "m_ru": "Контейнер для льда",
        "m_ko": "얼음 저장기",
        "m_ja": "氷を保存する器",
        "m_th": "ถาดใส่น้ำแข็ง",
        "m_id": "Tempat Penyimpanan Es Batu",
        "m_ms": "Bekas ais kiub",
        "unit": 5
    },
    {
        "w": "咖啡壶",
        "p": "kāfēi hú",
        "m": "Bình cà phê",
        "m_en": "Coffee Pot",
        "m_ru": "кофейник",
        "m_ko": "커피 포트( 커피 끓이는 그릇, coffee pot)。",
        "m_ja": "コ—ヒ—ポット",
        "m_th": "หม้อต้มกาแฟ",
        "m_id": "Pot kopi",
        "m_ms": "Periuk kopi",
        "unit": 5
    },
    {
        "w": "净水器",
        "p": "jìng shuǐ qì",
        "m": "Máy lọc nước",
        "m_en": "Water purifier",
        "m_ru": "водоочиститель, водоочистная установка; стационарный фильтр под мойку",
        "m_ko": "정수기。",
        "m_ja": "浄水器",
        "m_th": "เครื่องกรองน้ำ",
        "m_id": "Pemurni air",
        "m_ms": "Penapis air",
        "unit": 5
    },
    {
        "w": "开瓶器",
        "p": "kāi píng qì",
        "m": "Dụng cụ mở nắp chai",
        "m_en": "Bottle opener",
        "m_ru": "бутылочная открывалка, открывашка, штопор",
        "m_ko": "병따개。 오프너(opener)。",
        "m_ja": "栓抜き",
        "m_th": "ที่เปิดขวด",
        "m_id": "Pembuka botol",
        "m_ms": "Pembuka botol",
        "unit": 5
    },
    {
        "w": "冰箱",
        "p": "bīngxiāng",
        "m": "Tủ lạnh",
        "m_en": "Refrigerator",
        "m_ru": "ледник; холодильник",
        "m_ko": "아이스박스。; 전기냉장고의 약칭。  [冰柜] [冰橱] [冰桶(1)] [【남방어】 雪xuě柜]",
        "m_ja": "〔‘个・座’＋〕冷蔵庫，アイスボックス．≒雪柜．冷凍箱．氷箱",
        "m_th": "ตู้เย็น; ตู้แช่แข็ง",
        "m_id": "Kulkas",
        "m_ms": "Petisejuk; peti ais",
        "unit": 5
    },
    {
        "w": "玻璃杯",
        "p": "bōlí bēi",
        "m": "Cốc thuỷ tinh",
        "m_en": "Glass",
        "m_ru": "стеклянный стакан",
        "m_ko": "유리컵。 유리잔。",
        "m_ja": "ガラスのコップ",
        "m_th": "แก้วน้ำแก้ว; แก้วคริสตัล",
        "m_id": "Gelas kaca; gelas kristal",
        "m_ms": "Gelas kaca",
        "unit": 5
    },
    {
        "w": "饮水机",
        "p": "yǐnshuǐ jī",
        "m": "Máy lọc nước",
        "m_en": "Water Dispenser",
        "m_ru": "кулер для воды; нагреватель охладитель (питьевой) воды",
        "m_ko": "음수기。 생수 디스펜서(dispenser)。",
        "m_ja": "飲水機",
        "m_th": "เครื่องทำน้ำร้อนเย็น",
        "m_id": "Dispenser air panas dan dingin; mesin air panas dan dingin",
        "m_ms": "Mesin penyejuk dan pemanas air",
        "unit": 5
    },
    {
        "w": "热水瓶",
        "p": "rèshuǐpíng",
        "m": "Phích nước",
        "m_en": "Thermos Bottle",
        "m_ru": "термос",
        "m_ko": "열수병",
        "m_ja": "〔‘个’＋〕魔法瓶．≒暖水瓶．",
        "m_th": "กระติกน้ำร้อน",
        "m_id": "Termos; botol termos",
        "m_ms": "Termos; termos air",
        "unit": 5
    },
    {
        "w": "杯子水壶",
        "p": "bēizi shuǐhú",
        "m": "Cốc ấm đun nước",
        "m_en": "Cup and Kettle",
        "m_ru": "чашка для воды",
        "m_ko": "컵 물주전자",
        "m_ja": "カップとやかん",
        "m_th": "แก้ว; กาน้ำ",
        "m_id": "Cangkir; ketel air",
        "m_ms": "Cawan; cerek",
        "unit": 5
    },
    {
        "w": "杯子",
        "p": "bēizi",
        "m": "Cốc",
        "m_en": "Cup",
        "m_ru": "чашка, стакан, чарка, рюмка, бокал",
        "m_ko": "잔。",
        "m_ja": "〔‘个・只 zhī ’＋〕杯，グラス，コップ，茶わん，湯飲み．",
        "m_th": "แก้ว; ถ้วย",
        "m_id": "Gelas; cangkir",
        "m_ms": "Cawan; gelas",
        "unit": 5
    },
    {
        "w": "保温杯",
        "p": "bǎowēn bēi",
        "m": "Bình giữ nhiệt",
        "m_en": "Thermos Cup",
        "m_ru": "термокружка, стакан-термос",
        "m_ko": "보온 컵。",
        "m_ja": "魔法瓶",
        "m_th": "กระติกน้ำร้อน",
        "m_id": "Botol termos",
        "m_ms": "Bekas penebat haba",
        "unit": 5
    },
    {
        "w": "花边台布",
        "p": "huābiān táibù",
        "m": "Khăn trải bàn viền hoa",
        "m_en": "Lace tablecloth",
        "m_ru": "скатерть ретичелла",
        "m_ko": "꽃무늬 테이블보",
        "m_ja": "花柄のテーブルクロス",
        "m_th": "ผ้าปูโต๊ะขอบลูกไม้",
        "m_id": "Taplak meja renda",
        "m_ms": "Taplak meja renda",
        "unit": 4
    },
    {
        "w": "保鮮膜",
        "p": "bǎoxiān mó",
        "m": "Bọc thực phẩm",
        "m_en": "Plastic Wrap",
        "m_ru": "пленка для хранения продуктов",
        "m_ko": "비닐랩",
        "m_ja": "食品ラップ",
        "m_th": "ฟิล์มถนอมอาหาร",
        "m_id": "Plastik pembungkus makanan",
        "m_ms": "Pembalut makanan",
        "unit": 4
    },
    {
        "w": "日用百货",
        "p": "rì yòng bǎihuò",
        "m": "Hàng tiêu dùng",
        "m_en": "Daily necessities",
        "m_ru": "бытовые товары",
        "m_ko": "일용잡화",
        "m_ja": "日用雑貨",
        "m_th": "สินค้าอุปโภคบริโภค",
        "m_id": "Barang konsumsi",
        "m_ms": "Barangan pengguna",
        "unit": 4
    },
    {
        "w": "香茅",
        "p": "xiāng máo",
        "m": "Sả",
        "m_en": "Lemongrass",
        "m_ru": "лемонграсс; лимонник",
        "m_ko": "레몬그라스(lemon grass)。; 시트론。",
        "m_ja": "レモングラス",
        "m_th": "ตะไคร้; ต้นตะไคร้",
        "m_id": "Serai; tanaman serai",
        "m_ms": "Serai; pokok serai",
        "unit": 4
    },
    {
        "w": "测量",
        "p": "cèliáng",
        "m": "Đo, đong",
        "m_en": "Measure",
        "m_ru": "измерять; мерный",
        "m_ko": "[동사] 측량(하다)。",
        "m_ja": "測量する．メータリング．メジャメント．ミータレジ．レート",
        "m_th": "วัด; การวัด",
        "m_id": "Mengukur; pengukuran",
        "m_ms": "mengukur; pengukuran",
        "unit": 4
    },
    {
        "w": "淡",
        "p": "dàn",
        "m": "Nhạt",
        "m_en": "Mild",
        "m_ru": "слабый, жидкий; тонкий",
        "m_ko": "(액체나 기체 중에 포함된 어떤 성분이) 적다。 엷다。 희박하다。 (↔ 浓(1)); (맛이) 싱겁다。 (소금기가) 엷다。; (색이) 엷다。",
        "m_ja": "（色が）浅い，淡い，薄い．↔浓．甘かった．甘そうだろう．甘くないのでしたらば",
        "m_th": "จืด; จาง (รสชาติ)",
        "m_id": "Tawar; hambar (rasa)",
        "m_ms": "Tawar; hambar (rasa)",
        "unit": 4
    },
    {
        "w": "辣椒粉",
        "p": "làjiāo fěn",
        "m": "Ớt bột",
        "m_en": "Chili Powder",
        "m_ru": "молотый красный острый перец, порошок чили, паприка",
        "m_ko": "고추가루",
        "m_ja": "唐辛子粉",
        "m_th": "พริกป่น",
        "m_id": "Bubuk cabai",
        "m_ms": "Serbuk cili",
        "unit": 4
    },
    {
        "w": "抹布",
        "p": "mābù",
        "m": "Khăn lau",
        "m_en": "Rag",
        "m_ru": "тряпка (для пыли); обтирка",
        "m_ko": "[명사] 행주。 걸레。  →[搌zhǎn布]",
        "m_ja": "〔‘块・条’＋〕ふきん，ぞうきん．ティークロース",
        "m_th": "ผ้าเช็ด; ผ้าขี้ริ้ว",
        "m_id": "Kain lap; kain pel",
        "m_ms": "Kain lap",
        "unit": 4
    },
    {
        "w": "胡椒",
        "p": "hújiāo",
        "m": "Hạt tiêu",
        "m_en": "Pepper",
        "m_ru": "перец горошком",
        "m_ko": "후추。; 후추씨。",
        "m_ja": "コショウ．",
        "m_th": "พริกไทย",
        "m_id": "Lada",
        "m_ms": "Lada; lada hitam",
        "unit": 4
    },
    {
        "w": "炸",
        "p": "zhà",
        "m": "Rán, chiên",
        "m_en": "Deep-fry",
        "m_ru": "взорваться; лопнуть",
        "m_ko": "터지다。 파열하다。 폭발하다。; 폭파하다。 폭격하다。; 【구어】 (분노가) 폭발하다。 (화를) 터뜨리다。",
        "m_ja": "（コップ・ガラス瓶・ガラス板・魔法瓶などが突然）破裂する，割れる．",
        "m_th": "ระเบิด; ระเบิด",
        "m_id": "Meledak; Meledakkan",
        "m_ms": "Meletup; Meletup",
        "unit": 4
    },
    {
        "w": "清淡",
        "p": "qīng dàn",
        "m": "Thanh đạm",
        "m_en": "Light",
        "m_ru": "жидкий; светлый",
        "m_ko": "(맛·색깔 따위가) 담백하다。 산뜻하다。 연하다。 담담하다。; 불경기이다。 한산하다。 시세가 없다。",
        "m_ja": "（色・香りなどが）淡白である，あっさりしている，さっぱりしている．泊",
        "m_th": "เบา; จาง",
        "m_id": "Ringan; encer",
        "m_ms": "Ringan; cair",
        "unit": 4
    },
    {
        "w": "油爆",
        "p": "yóu bào",
        "m": "Xào lăn",
        "m_en": "Quick-fry",
        "m_ru": "масляное жарение",
        "m_ko": "기름에 튀기다",
        "m_ja": "油で炒めること",
        "m_th": "ผัดเผ็ด",
        "m_id": "Tumis",
        "m_ms": "Goreng kilas",
        "unit": 4
    },
    {
        "w": "给涂上油",
        "p": "gěitú shàng yóu",
        "m": "Cho thêm dầu ăn vào",
        "m_en": "Grease",
        "m_ru": "наносить масло",
        "m_ko": "기름을 바르다",
        "m_ja": "油を塗る",
        "m_th": "เติมน้ำมันพืช",
        "m_id": "Tambahkan minyak goreng",
        "m_ms": "Tambah minyak masak",
        "unit": 4
    },
    {
        "w": "耗油",
        "p": "hào yóu",
        "m": "Dầu hào",
        "m_en": "Oyster Sauce",
        "m_ru": "расход масла",
        "m_ko": "소모유",
        "m_ja": "燃料油を消費する，（一般に）ガソリンを消費する．",
        "m_th": "น้ำมันหอยนางรม",
        "m_id": "Saus tiram",
        "m_ms": "Sos tiram",
        "unit": 4
    },
    {
        "w": "椰子油",
        "p": "yē zǐ yóu",
        "m": "Dầu dừa",
        "m_en": "Coconut oil",
        "m_ru": "кокосовое масло",
        "m_ko": "야자유。  [椰油]",
        "m_ja": "ココナッツオイル",
        "m_th": "น้ำมันมะพร้าว",
        "m_id": "Minyak kelapa",
        "m_ms": "Minyak kelapa",
        "unit": 4
    },
    {
        "w": "酱油",
        "p": "jiàngyóu",
        "m": "Nước tương",
        "m_en": "Soy Sauce",
        "m_ru": "соевый соус",
        "m_ko": "간장。",
        "m_ja": "しょうゆ．紫．下地",
        "m_th": "ซีอิ๊ว; น้ำซอส",
        "m_id": "Kecap asin",
        "m_ms": "Kicap",
        "unit": 4
    },
    {
        "w": "油腻",
        "p": "yóunì",
        "m": "Ngấy",
        "m_en": "Greasy",
        "m_ru": "жирный; жирная пища",
        "m_ko": "기름지다。 기름기가 많다。",
        "m_ja": "（食物が）脂っこい，（物体に）油がべったりついている．",
        "m_th": "มัน; เลี่ยน",
        "m_id": "Berminyak; mengandung banyak minyak",
        "m_ms": "Berminyak; berlemak",
        "unit": 4
    },
    {
        "w": "精制油",
        "p": "jīngzhì yóu",
        "m": "Dầu tinh chế",
        "m_en": "Refined oil",
        "m_ru": "пищ. рафинированное масло; обработанная нефть, очищенная нефть, светлый нефтепродукт",
        "m_ko": "정제유",
        "m_ja": "精製油",
        "m_th": "น้ำมันกลั่น",
        "m_id": "Minyak olahan",
        "m_ms": "Minyak yang ditapis",
        "unit": 4
    },
    {
        "w": "橄榄油",
        "p": "gǎnlǎn yóu",
        "m": "Dầu ôliu",
        "m_en": "Olive oil",
        "m_ru": "оливковое (прованское) масло",
        "m_ko": "올리브유。",
        "m_ja": "オリーブオイル",
        "m_th": "น้ำมันมะกอก",
        "m_id": "Minyak zaitun",
        "m_ms": "Minyak zaitun",
        "unit": 4
    },
    {
        "w": "芝麻油",
        "p": "zhīmayóu",
        "m": "Dầu mè, dầu vừng",
        "m_en": "Sesame oil",
        "m_ru": "кунжутное масло",
        "m_ko": "참기름。  [香油(2)]",
        "m_ja": "ごまあぶら。",
        "m_th": "น้ำมันงา",
        "m_id": "Minyak wijen",
        "m_ms": "Minyak bijan",
        "unit": 4
    },
    {
        "w": "花生油",
        "p": "huāshēngyóu",
        "m": "Dầu lạc, dầu phộng",
        "m_en": "Peanut oil",
        "m_ru": "арахисовое масло",
        "m_ko": "땅콩기름。; 낙화생유",
        "m_ja": "ピーナッツ油",
        "m_th": "น้ำมันถั่วลิสง",
        "m_id": "Minyak kacang tanah",
        "m_ms": "Minyak kacang tanah",
        "unit": 4
    },
    {
        "w": "豆油",
        "p": "dòuyóu",
        "m": "Dầu đậu nành",
        "m_en": "Soybean oil",
        "m_ru": "бобовое (соевое) масло; диал. 酱油",
        "m_ko": "콩기름。; 대두유",
        "m_ja": "大豆油．",
        "m_th": "น้ำมันถั่วเหลือง",
        "m_id": "Minyak kedelai",
        "m_ms": "Minyak kacang soya",
        "unit": 4
    },
    {
        "w": "植物油",
        "p": "zhíwùyóu",
        "m": "Dầu thực vật",
        "m_en": "Vegetable oil",
        "m_ru": "растительное масло",
        "m_ko": "〈식물〉 식물유。  [【속어】 子油]",
        "m_ja": "植物から抽出された油",
        "m_th": "น้ำมันพืช; น้ำมันสมุนไพร",
        "m_id": "Minyak nabati",
        "m_ms": "Minyak sayuran",
        "unit": 4
    },
    {
        "w": "食油",
        "p": "shíyóu",
        "m": "Dầu ăn",
        "m_en": "Cooking oil",
        "m_ru": "пищевое масло",
        "m_ko": "식유。 식용유。",
        "m_ja": "食用油",
        "m_th": "น้ำมันพืช",
        "m_id": "Minyak goreng",
        "m_ms": "Minyak masak",
        "unit": 4
    },
    {
        "w": "蛋糕模",
        "p": "dàngāo mó",
        "m": "Khuôn làm bánh",
        "m_en": "Cake mold",
        "m_ru": "форма для торта",
        "m_ko": "케이크 틀",
        "m_ja": "ケーキ型",
        "m_th": "พิมพ์เค้ก",
        "m_id": "Cetakan kue",
        "m_ms": "Acuan kek",
        "unit": 3
    },
    {
        "w": "紫砂茶壶",
        "p": "zǐshā cháhú",
        "m": "Bình trà gốm",
        "m_en": "Yixing Clay Teapot",
        "m_ru": "глиняный / керамический заварочный чайник",
        "m_ko": "자사차주",
        "m_ja": "紫砂の茶壺",
        "m_th": "กาน้ำชาเซรามิก",
        "m_id": "Teko keramik",
        "m_ms": "Teko teh seramik",
        "unit": 3
    },
    {
        "w": "饼模",
        "p": "bǐng mó",
        "m": "Khuôn làm bánh",
        "m_en": "Cake Mold",
        "m_ru": "форма для торта",
        "m_ko": "빵틀",
        "m_ja": "ビンモ型",
        "m_th": "แม่พิมพ์ทำขนม",
        "m_id": "Cetakan kue",
        "m_ms": "Acuan kek",
        "unit": 3
    },
    {
        "w": "瓷茶壶",
        "p": "cí cháhú",
        "m": "Bình trà sứ",
        "m_en": "Porcelain Teapot",
        "m_ru": "фарфоровый заварочный чайник",
        "m_ko": "도자기 차주전자",
        "m_ja": "陶磁器の茶壺",
        "m_th": "กาน้ำชาพอร์ซเลน",
        "m_id": "Teko teh porselen",
        "m_ms": "Teko teh porselin",
        "unit": 3
    },
    {
        "w": "调味品全套",
        "p": "tiáowèi pǐn quántào",
        "m": "Hộp đồ gia vị",
        "m_en": "Complete Set of Condiments",
        "m_ru": "приправы полного набора",
        "m_ko": "조미료 전체 세트",
        "m_ja": "調味料のフルセット",
        "m_th": "ชุดเครื่องปรุงรส",
        "m_id": "Perangkat bumbu lengkap",
        "m_ms": "Set rempah ratus",
        "unit": 3
    },
    {
        "w": "擀面板",
        "p": "gǎn miànbǎn",
        "m": "Tấm gỗ cán bột mì",
        "m_en": "Pastry Board",
        "m_ru": "доска для раскатки теста",
        "m_ko": "밀대판",
        "m_ja": "麺棒",
        "m_th": "ถาดรีดแป้ง",
        "m_id": "Papan penggiling adonan",
        "m_ms": "Papan penggiling",
        "unit": 3
    },
    {
        "w": "华夫饼机",
        "p": "huá fū bǐng jī",
        "m": "máy làm bánh quế",
        "m_en": "Waffle Maker",
        "m_ru": "вафельница",
        "m_ko": "와플 기계",
        "m_ja": "ワッフルメーカー",
        "m_th": "เครื่องทำวาฟเฟิล",
        "m_id": "Mesin pembuat wafel",
        "m_ms": "Mesin pembuat waffle",
        "unit": 3
    },
    {
        "w": "大火翻炒",
        "p": "dàhuǒ fān chǎo",
        "m": "Xào trên lửa to",
        "m_en": "Stir-fry on high heat",
        "m_ru": "Большой огонь, жарить, обжаривать.",
        "m_ko": "대화 볶음",
        "m_ja": "強火で炒める",
        "m_th": "ผัดด้วยไฟแรง",
        "m_id": "Tumis dengan api besar",
        "m_ms": "Goreng dengan api besar",
        "unit": 3
    },
    {
        "w": "调羹",
        "p": "tiáogēng",
        "m": "Thìa canh",
        "m_en": "Spoon",
        "m_ru": "суповая ложка (китайская); хорошо варить суп, вкусно готовить",
        "m_ko": "국 숟가락。",
        "m_ja": "≒汤匙 tāngchí ．",
        "m_th": "ช้อน; ทัพพี",
        "m_id": "Sendok; sendok sup",
        "m_ms": "Sudip; sudu sup",
        "unit": 3
    },
    {
        "w": "碗橱",
        "p": "wǎn chú",
        "m": "Tủ để bát",
        "m_en": "Cupboard",
        "m_ru": "посудный шкаф, буфет",
        "m_ko": "찬장。",
        "m_ja": "〔‘个・座’＋〕食器戸棚，水屋．",
        "m_th": "ตู้เก็บชาม",
        "m_id": "Lemari mangkuk",
        "m_ms": "Kabinet mangkuk",
        "unit": 3
    },
    {
        "w": "洗碗机",
        "p": "xǐ wǎn jī",
        "m": "Máy rửa bát",
        "m_en": "Dishwasher",
        "m_ru": "посудомоечная машина",
        "m_ko": "식기세척기。",
        "m_ja": "食器洗い機",
        "m_th": "เครื่องล้างจาน",
        "m_id": "Mesin pencuci piring",
        "m_ms": "Mesin basuh pinggan mangkuk",
        "unit": 3
    },
    {
        "w": "电火锅",
        "p": "diàn huǒguō",
        "m": "Nồi lẩu điện",
        "m_en": "Electric Hot Pot",
        "m_ru": "электрическая жаровня (electric chafing dish)",
        "m_ko": "전기 냄비",
        "m_ja": "電気鍋",
        "m_th": "หม้อสุกี้ไฟฟ้า",
        "m_id": "Panci hotpot listrik",
        "m_ms": "Periuk steamboat elektrik",
        "unit": 3
    },
    {
        "w": "双层锅",
        "p": "shuāng céng guō",
        "m": "Nồi hai tầng",
        "m_en": "Double Boiler",
        "m_ru": "пароварка",
        "m_ko": "이중 냄비",
        "m_ja": "二重鍋",
        "m_th": "หม้อสองชั้น",
        "m_id": "Panci dua tingkat",
        "m_ms": "Periuk dua tingkat",
        "unit": 3
    },
    {
        "w": "不粘底平底煎锅",
        "p": "bù nián dǐ píngdǐ jiān guō",
        "m": "Chảo rán chống dính",
        "m_en": "Non-Stick Frying Pan",
        "m_ru": "нержавеющая сковорода с антипригарным покрытием",
        "m_ko": "비점착 바닥 프라이팬",
        "m_ja": "ノンスティックフライパン",
        "m_th": "กระทะทอดเคลือบสารกันติด",
        "m_id": "Penggorengan anti lengket",
        "m_ms": "Kuali leper tidak melekat",
        "unit": 3
    },
    {
        "w": "无油锅",
        "p": "wúyóu guō",
        "m": "Nồi chiên không dầu",
        "m_en": "Non-stick pan",
        "m_ru": "безмасляная сковорода",
        "m_ko": "무기름 팬",
        "m_ja": "ノンフライヤー",
        "m_th": "หม้อทอดไร้น้ำมัน",
        "m_id": "Penggorengan tanpa minyak",
        "m_ms": "Periuk penggoreng tanpa minyak",
        "unit": 3
    },
    {
        "w": "压力锅",
        "p": "yālìguō",
        "m": "Nồi áp suất",
        "m_en": "Pressure Cooker",
        "m_ru": "скороварка",
        "m_ko": "압력 솥。",
        "m_ja": "圧力鍋",
        "m_th": "หม้ออัดแรงดัน",
        "m_id": "Panci tekanan",
        "m_ms": "Periuk tekanan",
        "unit": 3
    },
    {
        "w": "蒸锅",
        "p": "zhēng guō",
        "m": "Nồi hấp",
        "m_en": "Steamer",
        "m_ru": "кастрюля для готовки на пару, пароварка, мантоварка; тех. испаритель",
        "m_ko": "찜통。 찜솥。",
        "m_ja": "蒸し器．蒸しなべ．キャセロール",
        "m_th": "หม้อนึ่ง; ชาม",
        "m_id": "kukusan; panci kukus",
        "m_ms": "kukusan; Pengukus",
        "unit": 3
    },
    {
        "w": "砂锅",
        "p": "shāguō",
        "m": "Nồi đất",
        "m_en": "Clay Pot",
        "m_ru": "горшок (на ножках, для варки)",
        "m_ko": "질냄비。 질솥。 뚝배기。 질그릇。 약탕관",
        "m_ja": "ほうろく",
        "m_th": "หม้อดินเผา",
        "m_id": "Panci tanah liat",
        "m_ms": "Periuk tanah liat",
        "unit": 3
    },
    {
        "w": "高压锅",
        "p": "gāoyāguō",
        "m": "Nồi áp suất",
        "m_en": "Pressure Cooker",
        "m_ru": "скороварка",
        "m_ko": "압력솥。 압력 냄비(autoclave)。",
        "m_ja": "压力锅．耐圧釜",
        "m_th": "หม้ออัดแรงดัน",
        "m_id": "Panci tekanan",
        "m_ms": "Periuk tekanan",
        "unit": 3
    },
    {
        "w": "电饭锅",
        "p": "diàn fàn guō",
        "m": "Nồi cơm điện",
        "m_en": "Rice Cooker",
        "m_ru": "электрическая рисоварка",
        "m_ko": "전기(밥)솥。",
        "m_ja": "≒电饭煲 diànfànbāo ．",
        "m_th": "หม้อหุงข้าวไฟฟ้า; หม้อไฟฟ้า",
        "m_id": "Penanak nasi listrik",
        "m_ms": "Periuk nasi elektrik",
        "unit": 3
    },
    {
        "w": "汤锅",
        "p": "tāngguō",
        "m": "Nồi hầm, nồi súp",
        "m_en": "Soup Pot",
        "m_ru": "мясник, мясная лавка (назв. по котлу, в котором обвариваются битые животные, чтобы облегчить удаление волосяного покрова; торгует главным образом свининой)",
        "m_ko": "냄비。 국솥。; 털을 뽑기 위해 도축한 동물을 튀기는 대형 솥。; 【비유】 도축장。 도살장。",
        "m_ja": "鍋",
        "m_th": "หม้อต้มน้ำขนาดใหญ่",
        "m_id": "Panci besar (panci untuk merebus air dan menghilangkan bulu ternak).",
        "m_ms": "periuk besar; periuk air panas (untuk mencabut bulu haiwan ternakan).",
        "unit": 3
    },
    {
        "w": "不粘锅",
        "p": "búpán guō",
        "m": "Chảo chống dính",
        "m_en": "Teflon-coated pan",
        "m_ru": "сковородка с антипригарным покрытием; не прилипать к сковороде",
        "m_ko": "코팅 처리가 된 프라이팬。",
        "m_ja": "ノンスティックフライパン",
        "m_th": "กระทะเคลือบสารกันติด",
        "m_id": "Wajan antilengket",
        "m_ms": "Kuali tidak melekat",
        "unit": 3
    },
    {
        "w": "平锅",
        "p": "píng guō",
        "m": "Chảo",
        "m_en": "Frying Pan",
        "m_ru": "кастрюля",
        "m_ko": "(바닥이 얕은) 냄비。",
        "m_ja": "フライパン",
        "m_th": "กระทะแบน",
        "m_id": "Penggorengan datar",
        "m_ms": "Kuali leper",
        "unit": 3
    },
    {
        "w": "锅",
        "p": "guō",
        "m": "Nồi",
        "m_en": "Pot",
        "m_ru": "сущ. /счётное слово; котёл, кастрюля, сковорода, сотейник",
        "m_ko": "냄비。 솥。 가마。; 가열용(加熱用)의 기구。; (锅儿) 보시기처럼 우묵한 부분。",
        "m_ja": "〔‘口’＋〕（煮たり炒めたりする時に用いる底の深いまたは浅い）なべ，かま．",
        "m_th": "หม้อ; ความผิด",
        "m_id": "Panci; periuk",
        "m_ms": "Periuk; Kesalahan",
        "unit": 3
    },
    {
        "w": "围裙",
        "p": "wéiqún",
        "m": "Tạp dề",
        "m_en": "Apron",
        "m_ru": "фартук; передник",
        "m_ko": "[명사] 앞치마。 에이프런(apron)。 →[油yóu裙]",
        "m_ja": "〔‘件・条’＋〕前掛け，エプロン．",
        "m_th": "ผ้ากันเปื้อน",
        "m_id": "Apron",
        "m_ms": "Apron",
        "unit": 2
    },
    {
        "w": "八角",
        "p": "bājiǎo",
        "m": "Hoa hồi",
        "m_en": "Star Anise",
        "m_ru": "восьмиугольный; восьмиугольник",
        "m_ko": "〈식물〉 팔각。 붓순나무。  [大茴香]; 〈식물〉 붓순나무의 열매。  [茴huí香]; 팔각(형)。",
        "m_ja": "八角ウイキョウ（常緑の低木で実が八角形をしている）．≒八角茴香，大茴香．",
        "m_th": "โป๊ยกั๊ก; แปดเหลี่ยม",
        "m_id": "Pohon adas bintang; adas bintang",
        "m_ms": "Pokok bunga lawang; bunga lawang",
        "unit": 2
    },
    {
        "w": "來自水",
        "p": "láizìshuǐ",
        "m": "Nước máy",
        "m_en": "Tap water",
        "m_ru": "приходить из воды",
        "m_ko": "물에서 오다",
        "m_ja": "水道水",
        "m_th": "น้ำประปา",
        "m_id": "Air keran",
        "m_ms": "Air paip",
        "unit": 2
    },
    {
        "w": "五味香",
        "p": "wǔwèi xiāng",
        "m": "Ngũ vị hương",
        "m_en": "Five Spice",
        "m_ru": "пять ароматов",
        "m_ko": "오미향",
        "m_ja": "五香粉",
        "m_th": "เครื่องเทศห้ารส",
        "m_id": "Lima Rempah",
        "m_ms": "Rempah Lima",
        "unit": 2
    },
    {
        "w": "桂皮",
        "p": "guìpí",
        "m": "Quế",
        "m_en": "Cinnamon",
        "m_ru": "коричник тамала, или коричник гималайский (лат. Cinnamomum tamala); кора коричного дерева",
        "m_ko": "〈식물〉 계피나무。; 계피나무의 껍질。; 〈약학〉 육계(肉桂)。 [건위(健胃)·강장제(强壯劑)로 씀]",
        "m_ja": "セイロン肉桂．≒锡兰肉桂．",
        "m_th": "ต้นอบเชย; เปลือกอบเชย",
        "m_id": "Pohon kayu manis; Kulit kayu manis",
        "m_ms": "Pokok kayu manis; Kulit kayu manis",
        "unit": 2
    },
    {
        "w": "秤",
        "p": "chèng",
        "m": "Cái cân",
        "m_en": "Scale",
        "m_ru": "весы; отвешивать",
        "m_ko": "저울。 [특히 대저울을 가리킴]",
        "m_ja": "〔‘杆・个’＋〕（多くさおばかりを指し）秤．⇒杆秤 gǎnchèng ，台秤 táichèng ．",
        "m_th": "ตาชั่ง; ตาชั่งคาน",
        "m_id": "Timbangan; timbangan batang",
        "m_ms": "Timbangan; dacing",
        "unit": 2
    },
    {
        "w": "海绵",
        "p": "hǎimián",
        "m": "Miếng xốp rửa bát",
        "m_en": "Sponge",
        "m_ru": "губка (напр., резиновая); губка (для мытья посуды)",
        "m_ko": "〈동물〉 해면。; 해면동물의 골격。; 스펀지。",
        "m_ja": "海綿，スポンジ．",
        "m_th": "ฟองน้ำทะเล; กระดูกพรุน",
        "m_id": "Spons; spons laut",
        "m_ms": "Span, span laut; Tulang span",
        "unit": 2
    },
    {
        "w": "料酒",
        "p": "liàojiǔ",
        "m": "Rượu nấu ăn",
        "m_en": "Cooking Wine",
        "m_ru": "вино для приготовления блюд",
        "m_ko": "요리할 때 쓰는 조미용 술。",
        "m_ja": "料理酒．（一般に紹興酒を用いる．）",
        "m_th": "เหล้าจีน (ใช้สำหรับปรุงอาหาร)",
        "m_id": "Anggur masak (digunakan untuk memasak)",
        "m_ms": "Arak masakan (digunakan untuk memasak makanan)",
        "unit": 2
    },
    {
        "w": "酸",
        "p": "suān",
        "m": "Chua",
        "m_en": "Sour",
        "m_ru": "кислый; квашеный",
        "m_ko": "〈화학〉 산。",
        "m_ja": "酸．⇒硫酸 liúsuān ，盐酸 yán‖suān ，强酸 qiángsuān ，弱酸 ruòsuān ．酸い",
        "m_th": "เปรี้ยว; เมื่อยล้า",
        "m_id": "Asam; Lelah",
        "m_ms": "Masam; Letih",
        "unit": 2
    },
    {
        "w": "食盐",
        "p": "shíyán",
        "m": "Muối ăn",
        "m_en": "Table salt",
        "m_ru": "поваренная соль",
        "m_ko": "[명사] 식염。  →[盐(1)]",
        "m_ja": "食塩．≒盐(通称) ，氯化钠．ソルト．波の花",
        "m_th": "เกลือ; เกลือบริโภค",
        "m_id": "Garam; garam dapur",
        "m_ms": "Garam; garam makan",
        "unit": 2
    },
    {
        "w": "醋",
        "p": "cù",
        "m": "Giấm",
        "m_en": "Vinegar",
        "m_ru": "уксус; ревность, ревнивое чувство, ревновать",
        "m_ko": "(식)초。; 【비유】 질투。 강샘。 샘。",
        "m_ja": "酢．",
        "m_th": "น้ำส้มสายชู; อิจฉา",
        "m_id": "Cuka; Cemburu",
        "m_ms": "Cuka; cemburu",
        "unit": 2
    },
    {
        "w": "苦",
        "p": "kǔ",
        "m": "Đắng",
        "m_en": "Bitter",
        "m_ru": "горький; терпкий",
        "m_ko": "쓰다。 ↔[甜tián(1)]; 고통스럽다。 고생스럽다。 고되다。 괴롭다。; 【방언】 (잘라서 제거하는 것이나 손실되는 것의 정도가) 지나치다。 심하다。 정도를 넘다。",
        "m_ja": "（味が）苦い．↔甘，甜．苦くなさそうでしょう．苦そうでしたらば．苦くなかったそうです; （気持ち・生活・仕事などが）苦しい，つらい，貧しい．⇒艰苦 jiānkǔ ，困苦 kùnkǔ ，贫苦 pínkǔ ，痛苦 tòngkǔ ．; (方言) 度を越している，極端である，ひどい．",
        "m_th": "ขม; เจ็บปวด",
        "m_id": "Pahit; Sakit",
        "m_ms": "Pahit; Sakit",
        "unit": 2
    },
    {
        "w": "味精",
        "p": "wèijīng",
        "m": "Mì chính (Bột ngọt)",
        "m_en": "MSG (Monosodium Glutamate)",
        "m_ru": "глутамат натрия (усилитель вкуса, приправа)",
        "m_ko": "〈화학〉 화학 조미료。  [【광동어】 味粉]; 미원",
        "m_ja": "〔‘包・袋・粒’＋〕化学調味料，味の素．≒味素，味之素．",
        "m_th": "ผงชูรส; มิชิ้น",
        "m_id": "Monosodium glutamat",
        "m_ms": "Perasa MSG",
        "unit": 2
    },
    {
        "w": "糖缸",
        "p": "táng gāng",
        "m": "Lọ đường",
        "m_en": "Sugar Jar",
        "m_ru": "сахарница",
        "m_ko": "설탕통",
        "m_ja": "砂糖入れ",
        "m_th": "โถน้ำตาล",
        "m_id": "Toples gula",
        "m_ms": "Balang gula",
        "unit": 2
    },
    {
        "w": "甜",
        "p": "tián",
        "m": "Ngọt",
        "m_en": "Sweet",
        "m_ru": "сладкий, вкусный; привлекательный, красивый, милый",
        "m_ko": "(맛이) 달다。; 【전용】 (말이) 달콤하다。; (생활이) 즐겁다。 행복하다。 기분 좋다。",
        "m_ja": "（味が）甘い．うまい．↔苦．⇒忆苦思甜 yì kǔ sī tián ．甘かった",
        "m_th": "หวาน; หวาน, หวานชื่น (เสียง, รอยยิ้ม, ปาก...)",
        "m_id": "Manis; Manis, menyenangkan (suara, senyuman, mulut...)",
        "m_ms": "Manis; Manis, menyenangkan (suara, senyuman, mulut...)",
        "unit": 2
    },
    {
        "w": "代糖",
        "p": "dài táng",
        "m": "Đường hóa học",
        "m_en": "Sugar substitute",
        "m_ru": "сахарозаменитель",
        "m_ko": "대체당",
        "m_ja": "人工甘味料",
        "m_th": "สารให้ความหวานแทนน้ำตาล",
        "m_id": "Pemanis buatan",
        "m_ms": "Pemanis tiruan",
        "unit": 2
    },
    {
        "w": "绵白糖",
        "p": "mián báitáng",
        "m": "Đường trắng",
        "m_en": "White granulated sugar",
        "m_ru": "рафинированный белый сахар, сахар-песок",
        "m_ko": "가루백설탕",
        "m_ja": "白砂糖",
        "m_th": "น้ำตาลทรายขาว",
        "m_id": "Gula putih",
        "m_ms": "Gula putih",
        "unit": 2
    },
    {
        "w": "糖粉",
        "p": "táng fěn",
        "m": "Đường bột",
        "m_en": "Powdered sugar",
        "m_ru": "сахарная пудра",
        "m_ko": "분당(粉糖)。 가루사탕。 설탕。",
        "m_ja": "粉砂糖",
        "m_th": "น้ำตาลไอซิ่ง",
        "m_id": "Gula bubuk, gula halus",
        "m_ms": "Gula serbuk, gula kisar",
        "unit": 2
    },
    {
        "w": "精制糖",
        "p": "jīngzhì táng",
        "m": "Đường tinh luyện, đường tinh chế",
        "m_en": "Refined sugar",
        "m_ru": "рафинированный сахар",
        "m_ko": "정제당",
        "m_ja": "精製された砂糖",
        "m_th": "น้ำตาลทรายขาว",
        "m_id": "Gula rafinasi",
        "m_ms": "Gula halus, gula halus.",
        "unit": 2
    },
    {
        "w": "放糖",
        "p": "fàng táng",
        "m": "Đường viên",
        "m_en": "Add sugar",
        "m_ru": "положить сахар",
        "m_ko": "설탕을 넣다",
        "m_ja": "砂糖の塊",
        "m_th": "น้ำตาลก้อน; เติมน้ำตาล",
        "m_id": "Gula batu; Menambahkan gula, menaruh gula",
        "m_ms": "Gula kiub; Tambah gula, masukkan gula",
        "unit": 2
    },
    {
        "w": "红糖",
        "p": "hóngtáng",
        "m": "Đường đỏ",
        "m_en": "Brown Sugar",
        "m_ru": "бурый (неочищенный) сахар",
        "m_ko": "[명사] 적사탕。 흑설탕。 홍탕。  [【방언】 黄糖] [赤砂(糖)] →[糖(2)] [砂糖]",
        "m_ja": "赤砂糖，黒砂糖．",
        "m_th": "น้ำตาลทรายแดง",
        "m_id": "Gula merah; gula tebu (belum mengkristal)",
        "m_ms": "Gula merah; gula tebu (belum mengkristal)",
        "unit": 2
    },
    {
        "w": "冰糖",
        "p": "bīngtáng",
        "m": "Đường phèn",
        "m_en": "Rock sugar",
        "m_ru": "леденцовый сахар, сахар-кандис; жарг. см. 海洛因 (слово употребляется в Шэньяне)",
        "m_ko": "얼음사탕。",
        "m_ja": "〔‘块’＋〕氷砂糖．",
        "m_th": "น้ำตาลกรวด",
        "m_id": "Gula batu",
        "m_ms": "Gula batu",
        "unit": 2
    },
    {
        "w": "砂糖",
        "p": "shātáng",
        "m": "Đường cát",
        "m_en": "Granulated sugar",
        "m_ru": "сахарный песок",
        "m_ko": "사탕。 굵은 설탕。",
        "m_ja": "砂糖．ズッケロ",
        "m_th": "น้ำตาลทราย",
        "m_id": "Gula pasir",
        "m_ms": "Gula pasir",
        "unit": 2
    },
    {
        "w": "糖",
        "p": "táng",
        "m": "Đường",
        "m_en": "Sugar",
        "m_ru": "сущ.; сахар, сладость, конфеты",
        "m_ko": "〈화학〉 탄수화물。 함수탄소。; 사탕。 설탕。; 엿。 사탕 과자。 캔디。 드롭스。",
        "m_ja": "（食用糖の総称）砂糖．⇒白糖 báitáng ，红糖 hóngtáng ，冰糖 bīngtáng ，方糖 fāngtáng ，砂糖 shātáng ．",
        "m_th": "น้ำตาล; สารน้ำตาล",
        "m_id": "gula; zat gula",
        "m_ms": "gula; bahan gula",
        "unit": 2
    },
    {
        "w": "牙签筒",
        "p": "yáqiān tǒng",
        "m": "Ống tăm",
        "m_en": "Toothpick holder",
        "m_ru": "держатель для зубочисток",
        "m_ko": "이쑤시개통。",
        "m_ja": "爪楊枝入れ",
        "m_th": "ที่ใส่ไม้จิ้มฟัน",
        "m_id": "Tabung tusuk gigi",
        "m_ms": "Bekas pencungkil gigi",
        "unit": 1
    },
    {
        "w": "塑胶筐",
        "p": "sùjiāo kuāng",
        "m": "Rổ nhựa",
        "m_en": "Plastic Basket",
        "m_ru": "пластиковая корзина",
        "m_ko": "플라스틱 바구니",
        "m_ja": "プラスチックバスケット",
        "m_th": "ตะกร้าพลาสติก",
        "m_id": "Keranjang plastik",
        "m_ms": "Bakul plastik",
        "unit": 1
    },
    {
        "w": "米柜",
        "p": "mǐ guì",
        "m": "Tủ đựng gạo",
        "m_en": "Rice Cabinet",
        "m_ru": "рисовый шкаф",
        "m_ko": "쌀궤",
        "m_ja": "米櫃",
        "m_th": "ตู้เก็บข้าว",
        "m_id": "Lemari beras",
        "m_ms": "Kabinet beras",
        "unit": 1
    },
    {
        "w": "餐具洗涤剂",
        "p": "cānjù xǐdí jì",
        "m": "Nước rửa chén",
        "m_en": "Dishwashing Detergent",
        "m_ru": "моющее средство для посуды",
        "m_ko": "식기 세척제",
        "m_ja": "食器用洗剤",
        "m_th": "น้ำยาล้างจาน",
        "m_id": "Cairan pencuci piring",
        "m_ms": "Pencuci pinggan",
        "unit": 1
    },
    {
        "w": "杯垫",
        "p": "bēi diàn",
        "m": "Lót cốc",
        "m_en": "Coaster",
        "m_ru": "подставка под стакан, костер",
        "m_ko": "coaster; 컵받침",
        "m_ja": "コースター",
        "m_th": "ที่รองแก้ว",
        "m_id": "Alas gelas",
        "m_ms": "Pad gelas",
        "unit": 1
    },
    {
        "w": "篮子",
        "p": "lánzi",
        "m": "Cái rổ",
        "m_en": "Basket",
        "m_ru": "корзина; корзинка",
        "m_ko": "바구니。 광주리。",
        "m_ja": "〔‘个・只 zhī’ ＋〕（手に提げるつるのついた）手提げかご，バスケット．⇒筐子 kuāng・zi ，菜篮子 càilán・zi ．",
        "m_th": "ตะกร้า; ลัง",
        "m_id": "Keranjang; bakul (terbuat dari rotan, bambu, atau plastik)",
        "m_ms": "Bakul",
        "unit": 1
    },
    {
        "w": "象牙筷",
        "p": "xiàngyá kuài",
        "m": "Đũa ngà",
        "m_en": "Ivory Chopsticks",
        "m_ru": "палочки для еды из слоновой кости",
        "m_ko": "상아 젓가락",
        "m_ja": "象牙で作られた箸",
        "m_th": "ตะเกียบงาช้าง",
        "m_id": "Gading gajah",
        "m_ms": "Penyepit gading",
        "unit": 1
    },
    {
        "w": "盘",
        "p": "pán",
        "m": "Đĩa",
        "m_en": "Plate",
        "m_ru": "умывальная раковина (древние времена); большая тарелка",
        "m_ko": "고대(古代)의 목욕·세면 용구의 일종。; 큰 접시。 [큰 것을 ‘盘子’ 작은 것을 ‘碟子’라 함]; 모양이나 기능이 쟁반·접시와 같은 것。",
        "m_ja": "（水を入れる木製の）洗面用具，たらい，水桶．パネル．プレート",
        "m_th": "อ่างล้างมือ (สมัยโบราณ); ถาด",
        "m_id": "Baskom cuci tangan (zaman dahulu); Nampan",
        "m_ms": "Basin cuci tangan (zaman dahulu); Dulang",
        "unit": 1
    },
    {
        "w": "纸巾",
        "p": "zhǐjīn",
        "m": "Giấy ăn",
        "m_en": "Paper Towel",
        "m_ru": "бумажная салфетка; бумажное полотенце",
        "m_ko": "티슈。",
        "m_ja": "清掃・除菌用の紙製クリーナー．",
        "m_th": "กระดาษทิชชู่",
        "m_id": "Tisu",
        "m_ms": "Tisu",
        "unit": 1
    },
    {
        "w": "银筷",
        "p": "yín kuài",
        "m": "Đũa bạc",
        "m_en": "Silver chopsticks",
        "m_ru": "серебряные палочки для еды",
        "m_ko": "은젓가락",
        "m_ja": "銀の箸",
        "m_th": "ตะเกียบเงิน",
        "m_id": "Sumpit perak",
        "m_ms": "Penyepit perak",
        "unit": 1
    },
    {
        "w": "桌布",
        "p": "zhuōbù",
        "m": "Khăn trải bàn",
        "m_en": "Tablecloth",
        "m_ru": "скатерть; комп. обои для рабочего стола",
        "m_ko": "테이블 보。",
        "m_ja": "〔‘块’＋〕テーブルクロス．≒台布．",
        "m_th": "ผ้าปูโต๊ะ",
        "m_id": "Taplak meja",
        "m_ms": "Kain alas meja",
        "unit": 1
    },
    {
        "w": "橱柜",
        "p": "chúguì",
        "m": "Tủ bát đĩa",
        "m_en": "Cabinet",
        "m_ru": "шкаф для посуды, буфет; столик с ящиками, тумбочка",
        "m_ko": "진열장。 찬장。 장식장。; 물건을 넣을 수 있는 낮은 탁자。",
        "m_ja": "食器棚，水屋．ドロア",
        "m_th": "ตู้กับข้าว; ตู้เคาน์เตอร์",
        "m_id": "Lemari dapur; lemari piring",
        "m_ms": "Kabinet dapur; Kabinet kaunter (kaunter rendah yang boleh digunakan sebagai meja)",
        "unit": 1
    },
    {
        "w": "塑料筷",
        "p": "sùliào kuài",
        "m": "Đũa nhựa",
        "m_en": "Plastic Chopsticks",
        "m_ru": "пластиковые палочки",
        "m_ko": "플라스틱 젓가락",
        "m_ja": "プラスチックの箸",
        "m_th": "ตะเกียบพลาสติก",
        "m_id": "Sumpit plastik",
        "m_ms": "Penyepit plastik",
        "unit": 1
    },
    {
        "w": "竹筷",
        "p": "zhú kuài",
        "m": "Đũa tre",
        "m_en": "Bamboo Chopsticks",
        "m_ru": "бамбуковые палочки для еды",
        "m_ko": "대나무 젓가락",
        "m_ja": "竹製の箸",
        "m_th": "ตะเกียบไม้ไผ่",
        "m_id": "Sumpit bambu",
        "m_ms": "Penyepit buluh",
        "unit": 1
    },
    {
        "w": "碗架",
        "p": "wǎnjià",
        "m": "Giá để bát đĩa",
        "m_en": "Dish rack",
        "m_ru": "подставка для тарелок",
        "m_ko": "그릇 받침대",
        "m_ja": "皿立て",
        "m_th": "ที่วางจานชาม",
        "m_id": "Rak piring mangkuk",
        "m_ms": "Rak pinggan mangkuk",
        "unit": 1
    },
    {
        "w": "餐巾",
        "p": "cānjīn",
        "m": "Khăn ăn",
        "m_en": "Napkin",
        "m_ru": "салфетка (столовая)",
        "m_ko": "(식탁용) 냅킨(napkin)。  [揩kāi嘴布]",
        "m_ja": "〔‘条・张・块’＋〕（食事時に口をふくための）ナプキン．≒餐布．",
        "m_th": "ผ้าเช็ดปาก; ผ้าเช็ดปาก (ผ้าสี่เหลี่ยมที่วางบนเข่าหรือหน้าอกเพื่อป้องกันไม่ให้เสื้อผ้าเปื้อนขณะรับประทานอาหาร)",
        "m_id": "Serbet makan",
        "m_ms": "Serbet meja",
        "unit": 1
    },
    {
        "w": "筷子架",
        "p": "kuàizi jià",
        "m": "Giá để đũa",
        "m_en": "Chopstick Holder",
        "m_ru": "держатель с палочками для еды",
        "m_ko": "(식사 때) 젓가락을 얹어 놓는 받침。",
        "m_ja": "箸置き",
        "m_th": "ที่วางตะเกียบ",
        "m_id": "Tempat sumpit",
        "m_ms": "Rak penyepit",
        "unit": 1
    },
    {
        "w": "碟子",
        "p": "diézi",
        "m": "Đĩa",
        "m_en": "Saucer",
        "m_ru": "маленькая тарелочка; блюдце",
        "m_ko": "접시。",
        "m_ja": "〔‘个・块’＋〕（‘盘子’より小さくて平たい）小皿．",
        "m_th": "จาน; จานใบหนึ่ง",
        "m_id": "Piring; piringan",
        "m_ms": "Pinggan; piring",
        "unit": 1
    },
    {
        "w": "餐具套装",
        "p": "cānjù tàozhuāng",
        "m": "Bộ đồ ăn theo bộ",
        "m_en": "Cutlery Set",
        "m_ru": "набор столовых приборов",
        "m_ko": "식기 세트",
        "m_ja": "食器セット",
        "m_th": "ชุดเครื่องใช้บนโต๊ะอาหาร",
        "m_id": "Peralatan makan set",
        "m_ms": "Set peralatan makan",
        "unit": 1
    },
    {
        "w": "筷子",
        "p": "kuài zi",
        "m": "Đũa",
        "m_en": "Chopsticks",
        "m_ru": "палочки (для еды)",
        "m_ko": "젓가락。",
        "m_ja": "〔‘双・根・把’＋〕箸．はし",
        "m_th": "ตะเกียบ; คู่ตะเกียบ",
        "m_id": "Stik; sepasang stik",
        "m_ms": "Penyepit; sepasang penyepit",
        "unit": 1
    },
    {
        "w": "餐具架",
        "p": "cānjù jià",
        "m": "Giá đựng bát",
        "m_en": "Cutlery Rack",
        "m_ru": "буфет, сервант; подставка для кухонных принадлежностей (ножей вилок, ложек)",
        "m_ko": "식기 건조대",
        "m_ja": "食器棚",
        "m_th": "ที่วางจานชาม",
        "m_id": "Rak piring",
        "m_ms": "Rak pinggan mangkuk",
        "unit": 1
    },
    {
        "w": "餐盘",
        "p": "cān pán",
        "m": "Khay đựng thức ăn",
        "m_en": "Dinner plate",
        "m_ru": "сервировочная тарелка",
        "m_ko": "식판",
        "m_ja": "皿",
        "m_th": "ถาดอาหาร",
        "m_id": "Nampan makanan",
        "m_ms": "Pinggan hidangan",
        "unit": 1
    },
    {
        "w": "盘子",
        "p": "pánzi",
        "m": "Cái mâm, khay",
        "m_en": "Dish",
        "m_ru": "тарелка; блюдо",
        "m_ko": "쟁반。; (옛날의) 매매 가격。 시장 가격。; 기생에게 주는 행하(行下)。 팁(tip)。",
        "m_ja": "〔‘套・个’＋〕物を載せるお盆，大皿．; (清末から中華人民共和国成立以前のいわゆる旧社会の言葉) 商品の相場．",
        "m_th": "ถาด; จาน",
        "m_id": "Nampan; piring",
        "m_ms": "Dulang; pinggan",
        "unit": 1
    },
    {
        "w": "餐具",
        "p": "cānjù",
        "m": "Bộ đồ ăn",
        "m_en": "Tableware",
        "m_ru": "столовый прибор",
        "m_ko": "식기(食器)。 식구(食具)。",
        "m_ja": "〔‘套・个’＋〕食器．",
        "m_th": "ชุดอาหาร; อุปกรณ์การกิน",
        "m_id": "Peralatan makan; alat makan",
        "m_ms": "Peralatan makan",
        "unit": 1
    },
    {
        "w": "纱罩",
        "p": "shāzhào",
        "m": "Lồng bàn",
        "m_en": "Mesh Cover",
        "m_ru": "марлевый колпак (для предохранения пищевых продуктов от мух); тех. пламегасительная сетка",
        "m_ko": "식탁용 덮개",
        "m_ja": "（食物にかぶせる）網の覆い，はい帳．",
        "m_th": "ฝาชี; โคมไฟ",
        "m_id": "Tudung saji; Kaca lampu",
        "m_ms": "Tudung saji; Kain lampu",
        "unit": 0
    },
    {
        "w": "铝箔",
        "p": "lǚbó",
        "m": "Giấy bạc, giấy nhôm",
        "m_en": "Aluminum Foil",
        "m_ru": "алюминиевая фольга",
        "m_ko": "알루미늄박。",
        "m_ja": "アルミ箔，アルミホイル．",
        "m_th": "ฟอยล์อลูมิเนียม",
        "m_id": "Kertas aluminium",
        "m_ms": "Kerajang aluminium",
        "unit": 0
    },
    {
        "w": "蒜苗",
        "p": "suànmiáo",
        "m": "Mầm tỏi",
        "m_en": "Garlic Sprouts",
        "m_ru": "молодые ростки чеснока",
        "m_ko": "마늘종。 산대。; 풋마늘。",
        "m_ja": "(方言)",
        "m_th": "ต้นกระเทียมอ่อน; กระเทียมสด",
        "m_id": "Bawang putih muda; tangkai bunga bawang putih muda",
        "m_ms": "Bawang putih muda; tangkai bunga bawang putih muda",
        "unit": 0
    },
    {
        "w": "鱼露",
        "p": "yú lù",
        "m": "Nước mắm",
        "m_en": "Fish Sauce",
        "m_ru": "рыбный соус; фиш-соус",
        "m_ko": "생선으로 만든 소스(sauce)。",
        "m_ja": "魚から作るしょうゆ，魚醬．",
        "m_th": "น้ำปลา",
        "m_id": "Saus ikan",
        "m_ms": "Sos ikan",
        "unit": 0
    },
    {
        "w": "姜黄",
        "p": "jiānghuáng",
        "m": "Nghệ",
        "m_en": "Turmeric",
        "m_ru": "куркума; турмерик",
        "m_ko": "강황。",
        "m_ja": "ウコン",
        "m_th": "ขมิ้น; ต้นขมิ้น",
        "m_id": "Kunyit; rimpang kunyit",
        "m_ms": "Kunyit; akar kunyit",
        "unit": 0
    },
    {
        "w": "姜",
        "p": "jiāng",
        "m": "Gừng",
        "m_en": "Ginger",
        "m_ru": "имбирь, корень имбиря, имбирь лекарственный (Zingiber officinale Rosc); Цзян (фамилия)",
        "m_ko": "〈식물〉 생강。; 성(姓)。",
        "m_ja": "ショウガ，ハジカミ．ジンジャー",
        "m_th": "ขิง; ขวง",
        "m_id": "Jahe; Keluarga Jiang",
        "m_ms": "Halia; Khong",
        "unit": 0
    },
    {
        "w": "蒜",
        "p": "suàn",
        "m": "Tỏi",
        "m_en": "Garlic",
        "m_ru": "чеснок; головка чеснока",
        "m_ko": "〈식물〉 마늘。",
        "m_ja": "〔‘棵’＋〕（植物）ニンニク．≒大蒜．",
        "m_th": "กระเทียม; ต้นกระเทียม",
        "m_id": "Bawang putih; bawang",
        "m_ms": "Bawang putih; bawang",
        "unit": 0
    },
    {
        "w": "葱",
        "p": "cōng",
        "m": "Hành",
        "m_en": "Scallion/Green Onion",
        "m_ru": "дудчатый лук, лук-татарка, татарка, лук-батун (Alium fistolosum); луковичные огородные растения",
        "m_ko": "〈식물〉 파。",
        "m_ja": "〔‘棵・根［儿］’＋〕ネギ．⇒大葱 dàcōng ，小葱 xiǎocōng ，洋葱 yángcōng ．",
        "m_th": "ต้นหอม",
        "m_id": "Bawang; tanaman bawang",
        "m_ms": "Bawang; pokok bawang",
        "unit": 0
    },
    {
        "w": "花椒",
        "p": "huājiāo",
        "m": "Hạt tiêu",
        "m_en": "Sichuan Pepper",
        "m_ru": "сычуаньский перец; зантоксилум",
        "m_ko": "〈식물〉 산초나무。; 산초나무 열매。",
        "m_ja": "（植物・種子）サンショウ．",
        "m_th": "พริกไทยเสฉวน; ต้นไม้พุ่มหรือไม้ต้นขนาดเล็กที่มีหนาม ผลเป็นรูปทรงกลม เมล็ดสีดำ ใช้เป็นเครื่องเทศหรือยา",
        "m_id": "Merica Sichuan; pohon merica Sichuan",
        "m_ms": "Pokok lada Sichuan; pokok Zanthoxylum.",
        "unit": 0
    },
    {
        "w": "熬",
        "p": "áo",
        "m": "Luộc",
        "m_en": "Boil",
        "m_ru": "варить; варить (для очистки или рафинации)",
        "m_ko": "(야채 따위를) 오래 삶다。 끓이다。; 오랫동안 끓이다。 (죽을) 쑤다。 [오랫동안 끓여 풀 같은 상태 또는 진한 액체로 만드는 것을 가리킴]; 달이다。 조리다。 제련하다。",
        "m_ja": "（穀物やにかわなどを糊状になるまで）長時間煮る，煮つめる，（漢方薬などを）煎じる，（スープなどを）煮出す．",
        "m_th": "เคี่ยว; อบแห้ง",
        "m_id": "Memasak dengan api kecil dalam waktu lama.; Mengeringkan",
        "m_ms": "Rebus; masak hingga lembut",
        "unit": 0
    },
    {
        "w": "辣椒",
        "p": "làjiāo",
        "m": "Ớt",
        "m_en": "Chili Pepper",
        "m_ru": "острый перец; перец чили",
        "m_ko": "〈식물〉 고추。",
        "m_ja": "（野菜）唐辛子．≒辣子．≧海椒(方言) ．とうがらし",
        "m_th": "พริก",
        "m_id": "Cabai",
        "m_ms": "Cili",
        "unit": 0
    },
    {
        "w": "蒸",
        "p": "zhēng",
        "m": "Hấp",
        "m_en": "Steam",
        "m_ru": "крупный черенок; толстый стебель (напр. очищенной конопли)",
        "m_ko": "증발하다。 김이 오르다。; 찌다。 (증기로) 데우다。",
        "m_ja": "蒸す，ふかす，蒸気を通す．蒸させた．蒸していなそうだ．蒸したらば．蒸させない; 水蒸気が上がる，湯気が上がる．",
        "m_th": "นึ่ง; การนึ่งน้ำ",
        "m_id": "Mengukus; Menguap",
        "m_ms": "Mengukus; Penyejatan",
        "unit": 0
    },
    {
        "w": "焯",
        "p": "chāo",
        "m": "Chần",
        "m_en": "Blanch",
        "m_ru": "zhuō прил., вм. 灼 (светлый, ясный, отчётливый); chāo гл. бланшировать, поместить продукты в кипящую воду на непродолжительное время",
        "m_ko": "【문어】 밝(게 빛나)다。 선명하다。 뚜렷하다。",
        "m_ja": "（野菜などを）ゆがく，湯通しする．≡绰2．",
        "m_th": "ลวก",
        "m_id": "Blansir; merebus sebentar (makanan)",
        "m_ms": "Blansir",
        "unit": 0
    },
    {
        "w": "烧开",
        "p": "shāo kāi",
        "m": "Đun sôi",
        "m_en": "Boil",
        "m_ru": "вскипятить, довести до кипения",
        "m_ko": "끓이다。",
        "m_ja": "沸かし",
        "m_th": "ต้มให้เดือด",
        "m_id": "Rebus",
        "m_ms": "Rebus",
        "unit": 0
    },
    {
        "w": "焖",
        "p": "mèn",
        "m": "Kho, om",
        "m_en": "Simmer",
        "m_ru": "гл.; томить (на медленном огне), тушить",
        "m_ko": "뜸을 들이다。 띄우다。 [뚜껑을 꼭 닫고 약한 불에 고거나 익히는 것]",
        "m_ja": "（きっちりふたをして）とろ火でゆっくり煮込む．",
        "m_th": "ตุ๋น; เคี่ยว",
        "m_id": "Memasak; merebus",
        "m_ms": "Memasak; merebus",
        "unit": 0
    },
    {
        "w": "烤",
        "p": "kǎo",
        "m": "Nướng",
        "m_en": "Roast",
        "m_ru": "греть (у огня, у печи); сушить (у огня, у печки)",
        "m_ko": "(불에) 굽다。; 불에 쬐여 말리다。; (불을) 쪼이다。 쬐다。",
        "m_ja": "あぶる，焼く，火で乾かす．",
        "m_th": "ย่าง; อบ",
        "m_id": "Memanggang; menghangatkan",
        "m_ms": "Memanggang; memanaskan",
        "unit": 0
    },
    {
        "w": "涮",
        "p": "shuàn",
        "m": "Nhúng",
        "m_en": "Swish (in hot pot)",
        "m_ru": "полоскать, споласкивать, мыть; вымачивать, размачивать",
        "m_ko": "물로[물에 담가] 흔들어 씻다。 헹구(어 씻어 내)다。 부시다。; (기물 안에) 물을 담고[붓고] 흔들어 씻다。; 【속어】 (거짓말을 하여) 속이다。",
        "m_ja": "（手・物を水の中に入れて）すすぐ，ゆすぐ，すすぎ洗いをする．",
        "m_th": "ล้าง; ลวก",
        "m_id": "Mencuci; Berkumur",
        "m_ms": "Basuh; Bilas",
        "unit": 0
    },
    {
        "w": "煎",
        "p": "jiān",
        "m": "Chiên",
        "m_en": "Pan-fry",
        "m_ru": "выпаривать; подсушивать",
        "m_ko": "(기름에) 지지다。 (전을) 부치다。 [‘炸zhá’는 많은 양의 기름을 사용하여 튀기는 것이고, ‘煎’은 기름을 프라이팬 등에 얇게 발라서 지지거나 부치는 것임]; (약·차 등을) 달이다。 졸이다。; 마음을 졸이다。 괴로움을 당하다。 시달리다。",
        "m_ja": "（少量の油で両面がキツネ色になるまで）焼く，煎る．（‘炸’ほど油の量は多くなく，‘炒’のようにかきまぜることはしない．）; （薬を）煎じる，（茶を）煮出す．",
        "m_th": "ทอด; ผัด",
        "m_id": "Menggoreng; Merebus",
        "m_ms": "Goreng; Merebus",
        "unit": 0
    },
    {
        "w": "炒",
        "p": "chǎo",
        "m": "Rang",
        "m_en": "Sauté",
        "m_ru": "поджаривать, жарить (в глубокой сковородке с малым добавлением масла на большом огне, активно перемешивая и подбрасывая на сковородке); калить, сушить",
        "m_ko": "(기름 따위로) 볶다。; (이득을 얻기 위해) 전매하다。 투기하다。 전매하여 이를 남기다。; 【방언】 해고하다。",
        "m_ja": "．いためれ．いためよ．いためる．いためろ",
        "m_th": "ผัด; ทอด",
        "m_id": "Menumis; menggoreng",
        "m_ms": "menumis; goreng",
        "unit": 0
    },
    {
        "w": "烹",
        "p": "pēng",
        "m": "Rim",
        "m_en": "Cook (slow simmer)",
        "m_ru": "варить; стряпать",
        "m_ko": "삶다。 끓이다。; 볶다。 [요리 방법의 하나로, 끓는 기름에 넣어 약간 볶은 다음 간장 따위의 조미료를 넣고 빨리 휘저어 만든 것을 말함]; 위협하다。 놀라게 하다。 ｢把他烹走了; 그를 위협하여 쫓아 버렸다。",
        "m_ja": "（食物を）煮る．⇒兔死狗烹 tù sǐ gǒu pēng ．; （茶を）沸かす．",
        "m_th": "ปรุง; ต้ม",
        "m_id": "Memasak; merebus",
        "m_ms": "memasak; merebus",
        "unit": 0
    },
    {
        "w": "咸",
        "p": "xián",
        "m": "Mặn",
        "m_en": "Salty",
        "m_ru": "солёный, засоленный; всё, все, все вместе, в полном составе",
        "m_ko": "【문어】 전부。 모두。",
        "m_ja": "(文語文[昔の書き言葉]) いずれも，皆．からくなさそうです．かろうございまして．からくないらしかった．からかったらば",
        "m_th": "เค็ม",
        "m_id": "Asin",
        "m_ms": "Masin",
        "unit": 0
    },
    {
        "w": "煮",
        "p": "zhǔ",
        "m": "Nấu, Luộc",
        "m_en": "Boil",
        "m_ru": "варить; кипятить",
        "m_ko": "삶다。 익히다。 끓이다。",
        "m_ja": "煮る，炊く，ゆでる．ゆでよ．ゆでろ．ゆでれ",
        "m_th": "ต้ม; ตุ๋น",
        "m_id": "Memasak; merebus",
        "m_ms": "Memasak; merebus",
        "unit": 0
    },
    {
        "w": "炖",
        "p": "dùn",
        "m": "Hầm, ninh",
        "m_en": "Stew",
        "m_ru": "dùn варить (до разваривания), тушить (в большом количестве воды); разварной, разваренный",
        "m_ko": "(약한 불에 장시간) 고다。 푹 삶다。; 데우다。 덥히다。; 【남방어】 끓이다。",
        "m_ja": "（多く肉類の塊を水に入れてとろ火で柔らかくなるまで）長時間ぐつぐつ煮る，煮込む．",
        "m_th": "ตุ๋น; ต้ม",
        "m_id": "Merebus; memasak dengan api kecil hingga empuk (sering digunakan untuk daging).",
        "m_ms": "Merebus; menanak",
        "unit": 0
    },
    {
        "w": "腌",
        "p": "yān",
        "m": "Muối",
        "m_en": "Marinate (meat)",
        "m_ru": "yān замачивать, выдерживать (напр., в соли, сахаре, соевом соусе, алкоголе), мариновать, засаливать, засахаривать; ā грязный, засаленный, вонючий",
        "m_ko": "(소금·설탕·간장·술 따위에) 절이다。",
        "m_ja": "（魚・肉・卵・野菜・果物などを塩・砂糖・みそ・油などで）漬ける．つけれ．つけろ．つけよ．つけ",
        "m_th": "ดอง; หมัก",
        "m_id": "Mengasinkan; merendam",
        "m_ms": "Perap; garam",
        "unit": 0
    }
]